{"data":{"__schema":{"types":[{"name":"Aggregate","kind":"OBJECT"},{"name":"Asset","kind":"OBJECT"},{"name":"AssetConnectInput","kind":"INPUT_OBJECT"},{"name":"AssetConnection","kind":"OBJECT"},{"name":"AssetCreateInput","kind":"INPUT_OBJECT"},{"name":"AssetCreateLocalizationDataInput","kind":"INPUT_OBJECT"},{"name":"AssetCreateLocalizationInput","kind":"INPUT_OBJECT"},{"name":"AssetCreateLocalizationsInput","kind":"INPUT_OBJECT"},{"name":"AssetCreateManyInlineInput","kind":"INPUT_OBJECT"},{"name":"AssetCreateOneInlineInput","kind":"INPUT_OBJECT"},{"name":"AssetEdge","kind":"OBJECT"},{"name":"AssetManyWhereInput","kind":"INPUT_OBJECT"},{"name":"AssetOrderByInput","kind":"ENUM"},{"name":"AssetSingleRelationWhereInput","kind":"INPUT_OBJECT"},{"name":"AssetTransformationInput","kind":"INPUT_OBJECT"},{"name":"AssetUpdateInput","kind":"INPUT_OBJECT"},{"name":"AssetUpdateLocalizationDataInput","kind":"INPUT_OBJECT"},{"name":"AssetUpdateLocalizationInput","kind":"INPUT_OBJECT"},{"name":"AssetUpdateLocalizationsInput","kind":"INPUT_OBJECT"},{"name":"AssetUpdateManyInlineInput","kind":"INPUT_OBJECT"},{"name":"AssetUpdateManyInput","kind":"INPUT_OBJECT"},{"name":"AssetUpdateManyLocalizationDataInput","kind":"INPUT_OBJECT"},{"name":"AssetUpdateManyLocalizationInput","kind":"INPUT_OBJECT"},{"name":"AssetUpdateManyLocalizationsInput","kind":"INPUT_OBJECT"},{"name":"AssetUpdateManyWithNestedWhereInput","kind":"INPUT_OBJECT"},{"name":"AssetUpdateOneInlineInput","kind":"INPUT_OBJECT"},{"name":"AssetUpdateWithNestedWhereUniqueInput","kind":"INPUT_OBJECT"},{"name":"AssetUpload","kind":"OBJECT"},{"name":"AssetUploadError","kind":"OBJECT"},{"name":"AssetUploadRequestPostData","kind":"OBJECT"},{"name":"AssetUploadStatus","kind":"ENUM"},{"name":"AssetUploadWhereInput","kind":"INPUT_OBJECT"},{"name":"AssetUploadWhereStageInput","kind":"INPUT_OBJECT"},{"name":"AssetUpsertInput","kind":"INPUT_OBJECT"},{"name":"AssetUpsertLocalizationInput","kind":"INPUT_OBJECT"},{"name":"AssetUpsertWithNestedWhereUniqueInput","kind":"INPUT_OBJECT"},{"name":"AssetWhereComparatorInput","kind":"INPUT_OBJECT"},{"name":"AssetWhereInput","kind":"INPUT_OBJECT"},{"name":"AssetWhereStageInput","kind":"INPUT_OBJECT"},{"name":"AssetWhereUniqueInput","kind":"INPUT_OBJECT"},{"name":"AttributeKey","kind":"ENUM"},{"name":"BatchPayload","kind":"OBJECT"},{"name":"BlogAuthor","kind":"OBJECT"},{"name":"BlogAuthorConnectInput","kind":"INPUT_OBJECT"},{"name":"BlogAuthorConnection","kind":"OBJECT"},{"name":"BlogAuthorCreateInput","kind":"INPUT_OBJECT"},{"name":"BlogAuthorCreateLocalizationDataInput","kind":"INPUT_OBJECT"},{"name":"BlogAuthorCreateLocalizationInput","kind":"INPUT_OBJECT"},{"name":"BlogAuthorCreateLocalizationsInput","kind":"INPUT_OBJECT"},{"name":"BlogAuthorCreateManyInlineInput","kind":"INPUT_OBJECT"},{"name":"BlogAuthorCreateOneInlineInput","kind":"INPUT_OBJECT"},{"name":"BlogAuthorEdge","kind":"OBJECT"},{"name":"BlogAuthorManyWhereInput","kind":"INPUT_OBJECT"},{"name":"BlogAuthorOrderByInput","kind":"ENUM"},{"name":"BlogAuthorUpdateInput","kind":"INPUT_OBJECT"},{"name":"BlogAuthorUpdateLocalizationDataInput","kind":"INPUT_OBJECT"},{"name":"BlogAuthorUpdateLocalizationInput","kind":"INPUT_OBJECT"},{"name":"BlogAuthorUpdateLocalizationsInput","kind":"INPUT_OBJECT"},{"name":"BlogAuthorUpdateManyInlineInput","kind":"INPUT_OBJECT"},{"name":"BlogAuthorUpdateManyInput","kind":"INPUT_OBJECT"},{"name":"BlogAuthorUpdateManyLocalizationDataInput","kind":"INPUT_OBJECT"},{"name":"BlogAuthorUpdateManyLocalizationInput","kind":"INPUT_OBJECT"},{"name":"BlogAuthorUpdateManyLocalizationsInput","kind":"INPUT_OBJECT"},{"name":"BlogAuthorUpdateManyWithNestedWhereInput","kind":"INPUT_OBJECT"},{"name":"BlogAuthorUpdateOneInlineInput","kind":"INPUT_OBJECT"},{"name":"BlogAuthorUpdateWithNestedWhereUniqueInput","kind":"INPUT_OBJECT"},{"name":"BlogAuthorUpsertInput","kind":"INPUT_OBJECT"},{"name":"BlogAuthorUpsertLocalizationInput","kind":"INPUT_OBJECT"},{"name":"BlogAuthorUpsertWithNestedWhereUniqueInput","kind":"INPUT_OBJECT"},{"name":"BlogAuthorWhereComparatorInput","kind":"INPUT_OBJECT"},{"name":"BlogAuthorWhereInput","kind":"INPUT_OBJECT"},{"name":"BlogAuthorWhereStageInput","kind":"INPUT_OBJECT"},{"name":"BlogAuthorWhereUniqueInput","kind":"INPUT_OBJECT"},{"name":"BlogPage","kind":"OBJECT"},{"name":"BlogPageConnectInput","kind":"INPUT_OBJECT"},{"name":"BlogPageConnection","kind":"OBJECT"},{"name":"BlogPageCreateInput","kind":"INPUT_OBJECT"},{"name":"BlogPageCreateLocalizationDataInput","kind":"INPUT_OBJECT"},{"name":"BlogPageCreateLocalizationInput","kind":"INPUT_OBJECT"},{"name":"BlogPageCreateLocalizationsInput","kind":"INPUT_OBJECT"},{"name":"BlogPageCreateManyInlineInput","kind":"INPUT_OBJECT"},{"name":"BlogPageCreateOneInlineInput","kind":"INPUT_OBJECT"},{"name":"BlogPageEdge","kind":"OBJECT"},{"name":"BlogPageManyWhereInput","kind":"INPUT_OBJECT"},{"name":"BlogPageOrderByInput","kind":"ENUM"},{"name":"BlogPageUpdateInput","kind":"INPUT_OBJECT"},{"name":"BlogPageUpdateLocalizationDataInput","kind":"INPUT_OBJECT"},{"name":"BlogPageUpdateLocalizationInput","kind":"INPUT_OBJECT"},{"name":"BlogPageUpdateLocalizationsInput","kind":"INPUT_OBJECT"},{"name":"BlogPageUpdateManyInlineInput","kind":"INPUT_OBJECT"},{"name":"BlogPageUpdateManyInput","kind":"INPUT_OBJECT"},{"name":"BlogPageUpdateManyLocalizationDataInput","kind":"INPUT_OBJECT"},{"name":"BlogPageUpdateManyLocalizationInput","kind":"INPUT_OBJECT"},{"name":"BlogPageUpdateManyLocalizationsInput","kind":"INPUT_OBJECT"},{"name":"BlogPageUpdateManyWithNestedWhereInput","kind":"INPUT_OBJECT"},{"name":"BlogPageUpdateOneInlineInput","kind":"INPUT_OBJECT"},{"name":"BlogPageUpdateWithNestedWhereUniqueInput","kind":"INPUT_OBJECT"},{"name":"BlogPageUpsertInput","kind":"INPUT_OBJECT"},{"name":"BlogPageUpsertLocalizationInput","kind":"INPUT_OBJECT"},{"name":"BlogPageUpsertWithNestedWhereUniqueInput","kind":"INPUT_OBJECT"},{"name":"BlogPageWhereComparatorInput","kind":"INPUT_OBJECT"},{"name":"BlogPageWhereInput","kind":"INPUT_OBJECT"},{"name":"BlogPageWhereStageInput","kind":"INPUT_OBJECT"},{"name":"BlogPageWhereUniqueInput","kind":"INPUT_OBJECT"},{"name":"BlogPost","kind":"OBJECT"},{"name":"BlogPostBodyRichText","kind":"OBJECT"},{"name":"BlogPostBodyRichTextEmbeddedTypes","kind":"UNION"},{"name":"BlogPostConnectInput","kind":"INPUT_OBJECT"},{"name":"BlogPostConnection","kind":"OBJECT"},{"name":"BlogPostCreateInput","kind":"INPUT_OBJECT"},{"name":"BlogPostCreateLocalizationDataInput","kind":"INPUT_OBJECT"},{"name":"BlogPostCreateLocalizationInput","kind":"INPUT_OBJECT"},{"name":"BlogPostCreateLocalizationsInput","kind":"INPUT_OBJECT"},{"name":"BlogPostCreateManyInlineInput","kind":"INPUT_OBJECT"},{"name":"BlogPostCreateOneInlineInput","kind":"INPUT_OBJECT"},{"name":"BlogPostEdge","kind":"OBJECT"},{"name":"BlogPostManyWhereInput","kind":"INPUT_OBJECT"},{"name":"BlogPostOrderByInput","kind":"ENUM"},{"name":"BlogPostUpdateInput","kind":"INPUT_OBJECT"},{"name":"BlogPostUpdateLocalizationDataInput","kind":"INPUT_OBJECT"},{"name":"BlogPostUpdateLocalizationInput","kind":"INPUT_OBJECT"},{"name":"BlogPostUpdateLocalizationsInput","kind":"INPUT_OBJECT"},{"name":"BlogPostUpdateManyInlineInput","kind":"INPUT_OBJECT"},{"name":"BlogPostUpdateManyInput","kind":"INPUT_OBJECT"},{"name":"BlogPostUpdateManyLocalizationDataInput","kind":"INPUT_OBJECT"},{"name":"BlogPostUpdateManyLocalizationInput","kind":"INPUT_OBJECT"},{"name":"BlogPostUpdateManyLocalizationsInput","kind":"INPUT_OBJECT"},{"name":"BlogPostUpdateManyWithNestedWhereInput","kind":"INPUT_OBJECT"},{"name":"BlogPostUpdateOneInlineInput","kind":"INPUT_OBJECT"},{"name":"BlogPostUpdateWithNestedWhereUniqueInput","kind":"INPUT_OBJECT"},{"name":"BlogPostUpsertInput","kind":"INPUT_OBJECT"},{"name":"BlogPostUpsertLocalizationInput","kind":"INPUT_OBJECT"},{"name":"BlogPostUpsertWithNestedWhereUniqueInput","kind":"INPUT_OBJECT"},{"name":"BlogPostVariant","kind":"OBJECT"},{"name":"BlogPostVariantConnectInput","kind":"INPUT_OBJECT"},{"name":"BlogPostVariantConnection","kind":"OBJECT"},{"name":"BlogPostVariantCreateInput","kind":"INPUT_OBJECT"},{"name":"BlogPostVariantCreateLocalizationDataInput","kind":"INPUT_OBJECT"},{"name":"BlogPostVariantCreateLocalizationInput","kind":"INPUT_OBJECT"},{"name":"BlogPostVariantCreateLocalizationsInput","kind":"INPUT_OBJECT"},{"name":"BlogPostVariantCreateManyInlineInput","kind":"INPUT_OBJECT"},{"name":"BlogPostVariantCreateOneInlineInput","kind":"INPUT_OBJECT"},{"name":"BlogPostVariantEdge","kind":"OBJECT"},{"name":"BlogPostVariantManyWhereInput","kind":"INPUT_OBJECT"},{"name":"BlogPostVariantOrderByInput","kind":"ENUM"},{"name":"BlogPostVariantUpdateInput","kind":"INPUT_OBJECT"},{"name":"BlogPostVariantUpdateLocalizationDataInput","kind":"INPUT_OBJECT"},{"name":"BlogPostVariantUpdateLocalizationInput","kind":"INPUT_OBJECT"},{"name":"BlogPostVariantUpdateLocalizationsInput","kind":"INPUT_OBJECT"},{"name":"BlogPostVariantUpdateManyInlineInput","kind":"INPUT_OBJECT"},{"name":"BlogPostVariantUpdateManyInput","kind":"INPUT_OBJECT"},{"name":"BlogPostVariantUpdateManyLocalizationDataInput","kind":"INPUT_OBJECT"},{"name":"BlogPostVariantUpdateManyLocalizationInput","kind":"INPUT_OBJECT"},{"name":"BlogPostVariantUpdateManyLocalizationsInput","kind":"INPUT_OBJECT"},{"name":"BlogPostVariantUpdateManyWithNestedWhereInput","kind":"INPUT_OBJECT"},{"name":"BlogPostVariantUpdateOneInlineInput","kind":"INPUT_OBJECT"},{"name":"BlogPostVariantUpdateWithNestedWhereUniqueInput","kind":"INPUT_OBJECT"},{"name":"BlogPostVariantUpsertInput","kind":"INPUT_OBJECT"},{"name":"BlogPostVariantUpsertLocalizationInput","kind":"INPUT_OBJECT"},{"name":"BlogPostVariantUpsertWithNestedWhereUniqueInput","kind":"INPUT_OBJECT"},{"name":"BlogPostVariantWhereComparatorInput","kind":"INPUT_OBJECT"},{"name":"BlogPostVariantWhereInput","kind":"INPUT_OBJECT"},{"name":"BlogPostVariantWhereStageInput","kind":"INPUT_OBJECT"},{"name":"BlogPostVariantWhereUniqueInput","kind":"INPUT_OBJECT"},{"name":"BlogPostWhereComparatorInput","kind":"INPUT_OBJECT"},{"name":"BlogPostWhereInput","kind":"INPUT_OBJECT"},{"name":"BlogPostWhereStageInput","kind":"INPUT_OBJECT"},{"name":"BlogPostWhereUniqueInput","kind":"INPUT_OBJECT"},{"name":"BlogTeasersSection","kind":"OBJECT"},{"name":"BlogTeasersSectionConnectInput","kind":"INPUT_OBJECT"},{"name":"BlogTeasersSectionConnection","kind":"OBJECT"},{"name":"BlogTeasersSectionCreateInput","kind":"INPUT_OBJECT"},{"name":"BlogTeasersSectionCreateLocalizationDataInput","kind":"INPUT_OBJECT"},{"name":"BlogTeasersSectionCreateLocalizationInput","kind":"INPUT_OBJECT"},{"name":"BlogTeasersSectionCreateLocalizationsInput","kind":"INPUT_OBJECT"},{"name":"BlogTeasersSectionCreateManyInlineInput","kind":"INPUT_OBJECT"},{"name":"BlogTeasersSectionCreateOneInlineInput","kind":"INPUT_OBJECT"},{"name":"BlogTeasersSectionCreateWithPositionInput","kind":"INPUT_OBJECT"},{"name":"BlogTeasersSectionEdge","kind":"OBJECT"},{"name":"BlogTeasersSectionManyWhereInput","kind":"INPUT_OBJECT"},{"name":"BlogTeasersSectionOrderByInput","kind":"ENUM"},{"name":"BlogTeasersSectionUpdateInput","kind":"INPUT_OBJECT"},{"name":"BlogTeasersSectionUpdateLocalizationDataInput","kind":"INPUT_OBJECT"},{"name":"BlogTeasersSectionUpdateLocalizationInput","kind":"INPUT_OBJECT"},{"name":"BlogTeasersSectionUpdateLocalizationsInput","kind":"INPUT_OBJECT"},{"name":"BlogTeasersSectionUpdateManyInlineInput","kind":"INPUT_OBJECT"},{"name":"BlogTeasersSectionUpdateManyInput","kind":"INPUT_OBJECT"},{"name":"BlogTeasersSectionUpdateManyLocalizationDataInput","kind":"INPUT_OBJECT"},{"name":"BlogTeasersSectionUpdateManyLocalizationInput","kind":"INPUT_OBJECT"},{"name":"BlogTeasersSectionUpdateManyLocalizationsInput","kind":"INPUT_OBJECT"},{"name":"BlogTeasersSectionUpdateManyWithNestedWhereInput","kind":"INPUT_OBJECT"},{"name":"BlogTeasersSectionUpdateOneInlineInput","kind":"INPUT_OBJECT"},{"name":"BlogTeasersSectionUpdateWithNestedWhereUniqueAndPositionInput","kind":"INPUT_OBJECT"},{"name":"BlogTeasersSectionUpdateWithNestedWhereUniqueInput","kind":"INPUT_OBJECT"},{"name":"BlogTeasersSectionUpsertInput","kind":"INPUT_OBJECT"},{"name":"BlogTeasersSectionUpsertLocalizationInput","kind":"INPUT_OBJECT"},{"name":"BlogTeasersSectionUpsertWithNestedWhereUniqueAndPositionInput","kind":"INPUT_OBJECT"},{"name":"BlogTeasersSectionUpsertWithNestedWhereUniqueInput","kind":"INPUT_OBJECT"},{"name":"BlogTeasersSectionWhereInput","kind":"INPUT_OBJECT"},{"name":"BlogTeasersSectionWhereUniqueInput","kind":"INPUT_OBJECT"},{"name":"Boolean","kind":"SCALAR"},{"name":"ButtonCta","kind":"OBJECT"},{"name":"ButtonCtaConnectInput","kind":"INPUT_OBJECT"},{"name":"ButtonCtaConnection","kind":"OBJECT"},{"name":"ButtonCtaCreateInput","kind":"INPUT_OBJECT"},{"name":"ButtonCtaCreateLocalizationDataInput","kind":"INPUT_OBJECT"},{"name":"ButtonCtaCreateLocalizationInput","kind":"INPUT_OBJECT"},{"name":"ButtonCtaCreateLocalizationsInput","kind":"INPUT_OBJECT"},{"name":"ButtonCtaCreateManyInlineInput","kind":"INPUT_OBJECT"},{"name":"ButtonCtaCreateOneInlineInput","kind":"INPUT_OBJECT"},{"name":"ButtonCtaCreateWithPositionInput","kind":"INPUT_OBJECT"},{"name":"ButtonCtaEdge","kind":"OBJECT"},{"name":"ButtonCtaManyWhereInput","kind":"INPUT_OBJECT"},{"name":"ButtonCtaOrderByInput","kind":"ENUM"},{"name":"ButtonCtaParent","kind":"UNION"},{"name":"ButtonCtaParentConnectInput","kind":"INPUT_OBJECT"},{"name":"ButtonCtaParentCreateInput","kind":"INPUT_OBJECT"},{"name":"ButtonCtaParentCreateManyInlineInput","kind":"INPUT_OBJECT"},{"name":"ButtonCtaParentCreateOneInlineInput","kind":"INPUT_OBJECT"},{"name":"ButtonCtaParentCreateWithPositionInput","kind":"INPUT_OBJECT"},{"name":"ButtonCtaParentUpdateInput","kind":"INPUT_OBJECT"},{"name":"ButtonCtaParentUpdateManyInlineInput","kind":"INPUT_OBJECT"},{"name":"ButtonCtaParentUpdateManyWithNestedWhereInput","kind":"INPUT_OBJECT"},{"name":"ButtonCtaParentUpdateOneInlineInput","kind":"INPUT_OBJECT"},{"name":"ButtonCtaParentUpdateWithNestedWhereUniqueAndPositionInput","kind":"INPUT_OBJECT"},{"name":"ButtonCtaParentUpdateWithNestedWhereUniqueInput","kind":"INPUT_OBJECT"},{"name":"ButtonCtaParentUpsertWithNestedWhereUniqueAndPositionInput","kind":"INPUT_OBJECT"},{"name":"ButtonCtaParentUpsertWithNestedWhereUniqueInput","kind":"INPUT_OBJECT"},{"name":"ButtonCtaParentWhereInput","kind":"INPUT_OBJECT"},{"name":"ButtonCtaParentWhereUniqueInput","kind":"INPUT_OBJECT"},{"name":"ButtonCtaUpdateInput","kind":"INPUT_OBJECT"},{"name":"ButtonCtaUpdateLocalizationDataInput","kind":"INPUT_OBJECT"},{"name":"ButtonCtaUpdateLocalizationInput","kind":"INPUT_OBJECT"},{"name":"ButtonCtaUpdateLocalizationsInput","kind":"INPUT_OBJECT"},{"name":"ButtonCtaUpdateManyInlineInput","kind":"INPUT_OBJECT"},{"name":"ButtonCtaUpdateManyInput","kind":"INPUT_OBJECT"},{"name":"ButtonCtaUpdateManyLocalizationDataInput","kind":"INPUT_OBJECT"},{"name":"ButtonCtaUpdateManyLocalizationInput","kind":"INPUT_OBJECT"},{"name":"ButtonCtaUpdateManyLocalizationsInput","kind":"INPUT_OBJECT"},{"name":"ButtonCtaUpdateManyWithNestedWhereInput","kind":"INPUT_OBJECT"},{"name":"ButtonCtaUpdateOneInlineInput","kind":"INPUT_OBJECT"},{"name":"ButtonCtaUpdateWithNestedWhereUniqueAndPositionInput","kind":"INPUT_OBJECT"},{"name":"ButtonCtaUpdateWithNestedWhereUniqueInput","kind":"INPUT_OBJECT"},{"name":"ButtonCtaUpsertInput","kind":"INPUT_OBJECT"},{"name":"ButtonCtaUpsertLocalizationInput","kind":"INPUT_OBJECT"},{"name":"ButtonCtaUpsertWithNestedWhereUniqueAndPositionInput","kind":"INPUT_OBJECT"},{"name":"ButtonCtaUpsertWithNestedWhereUniqueInput","kind":"INPUT_OBJECT"},{"name":"ButtonCtaWhereInput","kind":"INPUT_OBJECT"},{"name":"ButtonCtaWhereUniqueInput","kind":"INPUT_OBJECT"},{"name":"ClothesSize","kind":"ENUM"},{"name":"ClothesVariants","kind":"OBJECT"},{"name":"ClothesVariantsConnectInput","kind":"INPUT_OBJECT"},{"name":"ClothesVariantsConnection","kind":"OBJECT"},{"name":"ClothesVariantsCreateInput","kind":"INPUT_OBJECT"},{"name":"ClothesVariantsCreateLocalizationDataInput","kind":"INPUT_OBJECT"},{"name":"ClothesVariantsCreateLocalizationInput","kind":"INPUT_OBJECT"},{"name":"ClothesVariantsCreateLocalizationsInput","kind":"INPUT_OBJECT"},{"name":"ClothesVariantsCreateManyInlineInput","kind":"INPUT_OBJECT"},{"name":"ClothesVariantsCreateOneInlineInput","kind":"INPUT_OBJECT"},{"name":"ClothesVariantsCreateWithPositionInput","kind":"INPUT_OBJECT"},{"name":"ClothesVariantsEdge","kind":"OBJECT"},{"name":"ClothesVariantsManyWhereInput","kind":"INPUT_OBJECT"},{"name":"ClothesVariantsOrderByInput","kind":"ENUM"},{"name":"ClothesVariantsParent","kind":"UNION"},{"name":"ClothesVariantsParentConnectInput","kind":"INPUT_OBJECT"},{"name":"ClothesVariantsParentCreateInput","kind":"INPUT_OBJECT"},{"name":"ClothesVariantsParentCreateManyInlineInput","kind":"INPUT_OBJECT"},{"name":"ClothesVariantsParentCreateOneInlineInput","kind":"INPUT_OBJECT"},{"name":"ClothesVariantsParentUpdateInput","kind":"INPUT_OBJECT"},{"name":"ClothesVariantsParentUpdateManyInlineInput","kind":"INPUT_OBJECT"},{"name":"ClothesVariantsParentUpdateManyWithNestedWhereInput","kind":"INPUT_OBJECT"},{"name":"ClothesVariantsParentUpdateOneInlineInput","kind":"INPUT_OBJECT"},{"name":"ClothesVariantsParentUpdateWithNestedWhereUniqueInput","kind":"INPUT_OBJECT"},{"name":"ClothesVariantsParentUpsertWithNestedWhereUniqueInput","kind":"INPUT_OBJECT"},{"name":"ClothesVariantsParentWhereInput","kind":"INPUT_OBJECT"},{"name":"ClothesVariantsParentWhereUniqueInput","kind":"INPUT_OBJECT"},{"name":"ClothesVariantsUpdateInput","kind":"INPUT_OBJECT"},{"name":"ClothesVariantsUpdateLocalizationDataInput","kind":"INPUT_OBJECT"},{"name":"ClothesVariantsUpdateLocalizationInput","kind":"INPUT_OBJECT"},{"name":"ClothesVariantsUpdateLocalizationsInput","kind":"INPUT_OBJECT"},{"name":"ClothesVariantsUpdateManyInlineInput","kind":"INPUT_OBJECT"},{"name":"ClothesVariantsUpdateManyInput","kind":"INPUT_OBJECT"},{"name":"ClothesVariantsUpdateManyLocalizationDataInput","kind":"INPUT_OBJECT"},{"name":"ClothesVariantsUpdateManyLocalizationInput","kind":"INPUT_OBJECT"},{"name":"ClothesVariantsUpdateManyLocalizationsInput","kind":"INPUT_OBJECT"},{"name":"ClothesVariantsUpdateManyWithNestedWhereInput","kind":"INPUT_OBJECT"},{"name":"ClothesVariantsUpdateOneInlineInput","kind":"INPUT_OBJECT"},{"name":"ClothesVariantsUpdateWithNestedWhereUniqueAndPositionInput","kind":"INPUT_OBJECT"},{"name":"ClothesVariantsUpdateWithNestedWhereUniqueInput","kind":"INPUT_OBJECT"},{"name":"ClothesVariantsUpsertInput","kind":"INPUT_OBJECT"},{"name":"ClothesVariantsUpsertLocalizationInput","kind":"INPUT_OBJECT"},{"name":"ClothesVariantsUpsertWithNestedWhereUniqueAndPositionInput","kind":"INPUT_OBJECT"},{"name":"ClothesVariantsUpsertWithNestedWhereUniqueInput","kind":"INPUT_OBJECT"},{"name":"ClothesVariantsWhereInput","kind":"INPUT_OBJECT"},{"name":"ClothesVariantsWhereUniqueInput","kind":"INPUT_OBJECT"},{"name":"CollectionPage","kind":"OBJECT"},{"name":"CollectionPageConnectInput","kind":"INPUT_OBJECT"},{"name":"CollectionPageConnection","kind":"OBJECT"},{"name":"CollectionPageCreateInput","kind":"INPUT_OBJECT"},{"name":"CollectionPageCreateLocalizationDataInput","kind":"INPUT_OBJECT"},{"name":"CollectionPageCreateLocalizationInput","kind":"INPUT_OBJECT"},{"name":"CollectionPageCreateLocalizationsInput","kind":"INPUT_OBJECT"},{"name":"CollectionPageCreateManyInlineInput","kind":"INPUT_OBJECT"},{"name":"CollectionPageCreateOneInlineInput","kind":"INPUT_OBJECT"},{"name":"CollectionPageEdge","kind":"OBJECT"},{"name":"CollectionPageManyWhereInput","kind":"INPUT_OBJECT"},{"name":"CollectionPageOrderByInput","kind":"ENUM"},{"name":"CollectionPageUpdateInput","kind":"INPUT_OBJECT"},{"name":"CollectionPageUpdateLocalizationDataInput","kind":"INPUT_OBJECT"},{"name":"CollectionPageUpdateLocalizationInput","kind":"INPUT_OBJECT"},{"name":"CollectionPageUpdateLocalizationsInput","kind":"INPUT_OBJECT"},{"name":"CollectionPageUpdateManyInlineInput","kind":"INPUT_OBJECT"},{"name":"CollectionPageUpdateManyInput","kind":"INPUT_OBJECT"},{"name":"CollectionPageUpdateManyLocalizationDataInput","kind":"INPUT_OBJECT"},{"name":"CollectionPageUpdateManyLocalizationInput","kind":"INPUT_OBJECT"},{"name":"CollectionPageUpdateManyLocalizationsInput","kind":"INPUT_OBJECT"},{"name":"CollectionPageUpdateManyWithNestedWhereInput","kind":"INPUT_OBJECT"},{"name":"CollectionPageUpdateOneInlineInput","kind":"INPUT_OBJECT"},{"name":"CollectionPageUpdateWithNestedWhereUniqueInput","kind":"INPUT_OBJECT"},{"name":"CollectionPageUpsertInput","kind":"INPUT_OBJECT"},{"name":"CollectionPageUpsertLocalizationInput","kind":"INPUT_OBJECT"},{"name":"CollectionPageUpsertWithNestedWhereUniqueInput","kind":"INPUT_OBJECT"},{"name":"CollectionPageWhereComparatorInput","kind":"INPUT_OBJECT"},{"name":"CollectionPageWhereInput","kind":"INPUT_OBJECT"},{"name":"CollectionPageWhereStageInput","kind":"INPUT_OBJECT"},{"name":"CollectionPageWhereUniqueInput","kind":"INPUT_OBJECT"},{"name":"Color","kind":"OBJECT"},{"name":"ColorInput","kind":"INPUT_OBJECT"},{"name":"ConnectPositionInput","kind":"INPUT_OBJECT"},{"name":"Cta","kind":"OBJECT"},{"name":"CtaConnectInput","kind":"INPUT_OBJECT"},{"name":"CtaConnection","kind":"OBJECT"},{"name":"CtaCreateInput","kind":"INPUT_OBJECT"},{"name":"CtaCreateLocalizationDataInput","kind":"INPUT_OBJECT"},{"name":"CtaCreateLocalizationInput","kind":"INPUT_OBJECT"},{"name":"CtaCreateLocalizationsInput","kind":"INPUT_OBJECT"},{"name":"CtaCreateManyInlineInput","kind":"INPUT_OBJECT"},{"name":"CtaCreateOneInlineInput","kind":"INPUT_OBJECT"},{"name":"CtaCreateWithPositionInput","kind":"INPUT_OBJECT"},{"name":"CtaEdge","kind":"OBJECT"},{"name":"CtaManyWhereInput","kind":"INPUT_OBJECT"},{"name":"CtaOrderByInput","kind":"ENUM"},{"name":"CtaParent","kind":"UNION"},{"name":"CtaParentConnectInput","kind":"INPUT_OBJECT"},{"name":"CtaParentCreateInput","kind":"INPUT_OBJECT"},{"name":"CtaParentCreateManyInlineInput","kind":"INPUT_OBJECT"},{"name":"CtaParentCreateOneInlineInput","kind":"INPUT_OBJECT"},{"name":"CtaParentUpdateInput","kind":"INPUT_OBJECT"},{"name":"CtaParentUpdateManyInlineInput","kind":"INPUT_OBJECT"},{"name":"CtaParentUpdateManyWithNestedWhereInput","kind":"INPUT_OBJECT"},{"name":"CtaParentUpdateOneInlineInput","kind":"INPUT_OBJECT"},{"name":"CtaParentUpdateWithNestedWhereUniqueInput","kind":"INPUT_OBJECT"},{"name":"CtaParentUpsertWithNestedWhereUniqueInput","kind":"INPUT_OBJECT"},{"name":"CtaParentWhereInput","kind":"INPUT_OBJECT"},{"name":"CtaParentWhereUniqueInput","kind":"INPUT_OBJECT"},{"name":"CtaUpdateInput","kind":"INPUT_OBJECT"},{"name":"CtaUpdateLocalizationDataInput","kind":"INPUT_OBJECT"},{"name":"CtaUpdateLocalizationInput","kind":"INPUT_OBJECT"},{"name":"CtaUpdateLocalizationsInput","kind":"INPUT_OBJECT"},{"name":"CtaUpdateManyInlineInput","kind":"INPUT_OBJECT"},{"name":"CtaUpdateManyInput","kind":"INPUT_OBJECT"},{"name":"CtaUpdateManyLocalizationDataInput","kind":"INPUT_OBJECT"},{"name":"CtaUpdateManyLocalizationInput","kind":"INPUT_OBJECT"},{"name":"CtaUpdateManyLocalizationsInput","kind":"INPUT_OBJECT"},{"name":"CtaUpdateManyWithNestedWhereInput","kind":"INPUT_OBJECT"},{"name":"CtaUpdateOneInlineInput","kind":"INPUT_OBJECT"},{"name":"CtaUpdateWithNestedWhereUniqueAndPositionInput","kind":"INPUT_OBJECT"},{"name":"CtaUpdateWithNestedWhereUniqueInput","kind":"INPUT_OBJECT"},{"name":"CtaUpsertInput","kind":"INPUT_OBJECT"},{"name":"CtaUpsertLocalizationInput","kind":"INPUT_OBJECT"},{"name":"CtaUpsertWithNestedWhereUniqueAndPositionInput","kind":"INPUT_OBJECT"},{"name":"CtaUpsertWithNestedWhereUniqueInput","kind":"INPUT_OBJECT"},{"name":"CtaWhereInput","kind":"INPUT_OBJECT"},{"name":"CtaWhereUniqueInput","kind":"INPUT_OBJECT"},{"name":"CtabuttonDetailsUnion","kind":"UNION"},{"name":"CtabuttonDetailsUnionConnectInput","kind":"INPUT_OBJECT"},{"name":"CtabuttonDetailsUnionCreateInput","kind":"INPUT_OBJECT"},{"name":"CtabuttonDetailsUnionCreateManyInlineInput","kind":"INPUT_OBJECT"},{"name":"CtabuttonDetailsUnionCreateOneInlineInput","kind":"INPUT_OBJECT"},{"name":"CtabuttonDetailsUnionCreateWithPositionInput","kind":"INPUT_OBJECT"},{"name":"CtabuttonDetailsUnionUpdateInput","kind":"INPUT_OBJECT"},{"name":"CtabuttonDetailsUnionUpdateManyInlineInput","kind":"INPUT_OBJECT"},{"name":"CtabuttonDetailsUnionUpdateManyWithNestedWhereInput","kind":"INPUT_OBJECT"},{"name":"CtabuttonDetailsUnionUpdateOneInlineInput","kind":"INPUT_OBJECT"},{"name":"CtabuttonDetailsUnionUpdateWithNestedWhereUniqueAndPositionInput","kind":"INPUT_OBJECT"},{"name":"CtabuttonDetailsUnionUpdateWithNestedWhereUniqueInput","kind":"INPUT_OBJECT"},{"name":"CtabuttonDetailsUnionUpsertWithNestedWhereUniqueAndPositionInput","kind":"INPUT_OBJECT"},{"name":"CtabuttonDetailsUnionUpsertWithNestedWhereUniqueInput","kind":"INPUT_OBJECT"},{"name":"CtabuttonDetailsUnionWhereInput","kind":"INPUT_OBJECT"},{"name":"CtabuttonDetailsUnionWhereUniqueInput","kind":"INPUT_OBJECT"},{"name":"Currency","kind":"ENUM"},{"name":"Date","kind":"SCALAR"},{"name":"DateTime","kind":"SCALAR"},{"name":"DocumentFileTypes","kind":"ENUM"},{"name":"DocumentOutputInput","kind":"INPUT_OBJECT"},{"name":"DocumentTransformationInput","kind":"INPUT_OBJECT"},{"name":"DocumentVersion","kind":"OBJECT"},{"name":"Entity","kind":"INTERFACE"},{"name":"EntityTypeName","kind":"ENUM"},{"name":"EntityWhereInput","kind":"INPUT_OBJECT"},{"name":"FakeStoreApi_FakeStoreProduct","kind":"OBJECT"},{"name":"FakeStoreApi_RemoteRating","kind":"OBJECT"},{"name":"FederateThisApi_Product","kind":"OBJECT"},{"name":"FederateThisApi_Products","kind":"OBJECT"},{"name":"Float","kind":"SCALAR"},{"name":"HeroSection","kind":"OBJECT"},{"name":"HeroSectionConnectInput","kind":"INPUT_OBJECT"},{"name":"HeroSectionConnection","kind":"OBJECT"},{"name":"HeroSectionCreateInput","kind":"INPUT_OBJECT"},{"name":"HeroSectionCreateLocalizationDataInput","kind":"INPUT_OBJECT"},{"name":"HeroSectionCreateLocalizationInput","kind":"INPUT_OBJECT"},{"name":"HeroSectionCreateLocalizationsInput","kind":"INPUT_OBJECT"},{"name":"HeroSectionCreateManyInlineInput","kind":"INPUT_OBJECT"},{"name":"HeroSectionCreateOneInlineInput","kind":"INPUT_OBJECT"},{"name":"HeroSectionCreateWithPositionInput","kind":"INPUT_OBJECT"},{"name":"HeroSectionEdge","kind":"OBJECT"},{"name":"HeroSectionManyWhereInput","kind":"INPUT_OBJECT"},{"name":"HeroSectionOrderByInput","kind":"ENUM"},{"name":"HeroSectionUpdateInput","kind":"INPUT_OBJECT"},{"name":"HeroSectionUpdateLocalizationDataInput","kind":"INPUT_OBJECT"},{"name":"HeroSectionUpdateLocalizationInput","kind":"INPUT_OBJECT"},{"name":"HeroSectionUpdateLocalizationsInput","kind":"INPUT_OBJECT"},{"name":"HeroSectionUpdateManyInlineInput","kind":"INPUT_OBJECT"},{"name":"HeroSectionUpdateManyInput","kind":"INPUT_OBJECT"},{"name":"HeroSectionUpdateManyLocalizationDataInput","kind":"INPUT_OBJECT"},{"name":"HeroSectionUpdateManyLocalizationInput","kind":"INPUT_OBJECT"},{"name":"HeroSectionUpdateManyLocalizationsInput","kind":"INPUT_OBJECT"},{"name":"HeroSectionUpdateManyWithNestedWhereInput","kind":"INPUT_OBJECT"},{"name":"HeroSectionUpdateOneInlineInput","kind":"INPUT_OBJECT"},{"name":"HeroSectionUpdateWithNestedWhereUniqueAndPositionInput","kind":"INPUT_OBJECT"},{"name":"HeroSectionUpdateWithNestedWhereUniqueInput","kind":"INPUT_OBJECT"},{"name":"HeroSectionUpsertInput","kind":"INPUT_OBJECT"},{"name":"HeroSectionUpsertLocalizationInput","kind":"INPUT_OBJECT"},{"name":"HeroSectionUpsertWithNestedWhereUniqueAndPositionInput","kind":"INPUT_OBJECT"},{"name":"HeroSectionUpsertWithNestedWhereUniqueInput","kind":"INPUT_OBJECT"},{"name":"HeroSectionWhereInput","kind":"INPUT_OBJECT"},{"name":"HeroSectionWhereUniqueInput","kind":"INPUT_OBJECT"},{"name":"HeroSlider","kind":"OBJECT"},{"name":"HeroSliderConnectInput","kind":"INPUT_OBJECT"},{"name":"HeroSliderConnection","kind":"OBJECT"},{"name":"HeroSliderCreateInput","kind":"INPUT_OBJECT"},{"name":"HeroSliderCreateLocalizationDataInput","kind":"INPUT_OBJECT"},{"name":"HeroSliderCreateLocalizationInput","kind":"INPUT_OBJECT"},{"name":"HeroSliderCreateLocalizationsInput","kind":"INPUT_OBJECT"},{"name":"HeroSliderCreateManyInlineInput","kind":"INPUT_OBJECT"},{"name":"HeroSliderCreateOneInlineInput","kind":"INPUT_OBJECT"},{"name":"HeroSliderCreateWithPositionInput","kind":"INPUT_OBJECT"},{"name":"HeroSliderEdge","kind":"OBJECT"},{"name":"HeroSliderManyWhereInput","kind":"INPUT_OBJECT"},{"name":"HeroSliderOrderByInput","kind":"ENUM"},{"name":"HeroSliderParent","kind":"UNION"},{"name":"HeroSliderParentConnectInput","kind":"INPUT_OBJECT"},{"name":"HeroSliderParentCreateInput","kind":"INPUT_OBJECT"},{"name":"HeroSliderParentCreateManyInlineInput","kind":"INPUT_OBJECT"},{"name":"HeroSliderParentCreateOneInlineInput","kind":"INPUT_OBJECT"},{"name":"HeroSliderParentUpdateInput","kind":"INPUT_OBJECT"},{"name":"HeroSliderParentUpdateManyInlineInput","kind":"INPUT_OBJECT"},{"name":"HeroSliderParentUpdateManyWithNestedWhereInput","kind":"INPUT_OBJECT"},{"name":"HeroSliderParentUpdateOneInlineInput","kind":"INPUT_OBJECT"},{"name":"HeroSliderParentUpdateWithNestedWhereUniqueInput","kind":"INPUT_OBJECT"},{"name":"HeroSliderParentUpsertWithNestedWhereUniqueInput","kind":"INPUT_OBJECT"},{"name":"HeroSliderParentWhereInput","kind":"INPUT_OBJECT"},{"name":"HeroSliderParentWhereUniqueInput","kind":"INPUT_OBJECT"},{"name":"HeroSliderUpdateInput","kind":"INPUT_OBJECT"},{"name":"HeroSliderUpdateLocalizationDataInput","kind":"INPUT_OBJECT"},{"name":"HeroSliderUpdateLocalizationInput","kind":"INPUT_OBJECT"},{"name":"HeroSliderUpdateLocalizationsInput","kind":"INPUT_OBJECT"},{"name":"HeroSliderUpdateManyInlineInput","kind":"INPUT_OBJECT"},{"name":"HeroSliderUpdateManyInput","kind":"INPUT_OBJECT"},{"name":"HeroSliderUpdateManyLocalizationDataInput","kind":"INPUT_OBJECT"},{"name":"HeroSliderUpdateManyLocalizationInput","kind":"INPUT_OBJECT"},{"name":"HeroSliderUpdateManyLocalizationsInput","kind":"INPUT_OBJECT"},{"name":"HeroSliderUpdateManyWithNestedWhereInput","kind":"INPUT_OBJECT"},{"name":"HeroSliderUpdateOneInlineInput","kind":"INPUT_OBJECT"},{"name":"HeroSliderUpdateWithNestedWhereUniqueAndPositionInput","kind":"INPUT_OBJECT"},{"name":"HeroSliderUpdateWithNestedWhereUniqueInput","kind":"INPUT_OBJECT"},{"name":"HeroSliderUpsertInput","kind":"INPUT_OBJECT"},{"name":"HeroSliderUpsertLocalizationInput","kind":"INPUT_OBJECT"},{"name":"HeroSliderUpsertWithNestedWhereUniqueAndPositionInput","kind":"INPUT_OBJECT"},{"name":"HeroSliderUpsertWithNestedWhereUniqueInput","kind":"INPUT_OBJECT"},{"name":"HeroSliderWhereInput","kind":"INPUT_OBJECT"},{"name":"HeroSliderWhereUniqueInput","kind":"INPUT_OBJECT"},{"name":"Hex","kind":"SCALAR"},{"name":"ID","kind":"SCALAR"},{"name":"ImageBlurInput","kind":"INPUT_OBJECT"},{"name":"ImageBorderInput","kind":"INPUT_OBJECT"},{"name":"ImageCompressInput","kind":"INPUT_OBJECT"},{"name":"ImageCropInput","kind":"INPUT_OBJECT"},{"name":"ImageFit","kind":"ENUM"},{"name":"ImageQualityInput","kind":"INPUT_OBJECT"},{"name":"ImageResizeInput","kind":"INPUT_OBJECT"},{"name":"ImageSharpenInput","kind":"INPUT_OBJECT"},{"name":"ImageTransformationInput","kind":"INPUT_OBJECT"},{"name":"Int","kind":"SCALAR"},{"name":"Json","kind":"SCALAR"},{"name":"LandingPage","kind":"OBJECT"},{"name":"LandingPageConnectInput","kind":"INPUT_OBJECT"},{"name":"LandingPageConnection","kind":"OBJECT"},{"name":"LandingPageCreateInput","kind":"INPUT_OBJECT"},{"name":"LandingPageCreateLocalizationDataInput","kind":"INPUT_OBJECT"},{"name":"LandingPageCreateLocalizationInput","kind":"INPUT_OBJECT"},{"name":"LandingPageCreateLocalizationsInput","kind":"INPUT_OBJECT"},{"name":"LandingPageCreateManyInlineInput","kind":"INPUT_OBJECT"},{"name":"LandingPageCreateOneInlineInput","kind":"INPUT_OBJECT"},{"name":"LandingPageEdge","kind":"OBJECT"},{"name":"LandingPageManyWhereInput","kind":"INPUT_OBJECT"},{"name":"LandingPageOrderByInput","kind":"ENUM"},{"name":"LandingPageUpdateInput","kind":"INPUT_OBJECT"},{"name":"LandingPageUpdateLocalizationDataInput","kind":"INPUT_OBJECT"},{"name":"LandingPageUpdateLocalizationInput","kind":"INPUT_OBJECT"},{"name":"LandingPageUpdateLocalizationsInput","kind":"INPUT_OBJECT"},{"name":"LandingPageUpdateManyInlineInput","kind":"INPUT_OBJECT"},{"name":"LandingPageUpdateManyInput","kind":"INPUT_OBJECT"},{"name":"LandingPageUpdateManyLocalizationDataInput","kind":"INPUT_OBJECT"},{"name":"LandingPageUpdateManyLocalizationInput","kind":"INPUT_OBJECT"},{"name":"LandingPageUpdateManyLocalizationsInput","kind":"INPUT_OBJECT"},{"name":"LandingPageUpdateManyWithNestedWhereInput","kind":"INPUT_OBJECT"},{"name":"LandingPageUpdateOneInlineInput","kind":"INPUT_OBJECT"},{"name":"LandingPageUpdateWithNestedWhereUniqueInput","kind":"INPUT_OBJECT"},{"name":"LandingPageUpsertInput","kind":"INPUT_OBJECT"},{"name":"LandingPageUpsertLocalizationInput","kind":"INPUT_OBJECT"},{"name":"LandingPageUpsertWithNestedWhereUniqueInput","kind":"INPUT_OBJECT"},{"name":"LandingPageWhereComparatorInput","kind":"INPUT_OBJECT"},{"name":"LandingPageWhereInput","kind":"INPUT_OBJECT"},{"name":"LandingPageWhereStageInput","kind":"INPUT_OBJECT"},{"name":"LandingPageWhereUniqueInput","kind":"INPUT_OBJECT"},{"name":"LandingPagemodularTestUnion","kind":"UNION"},{"name":"LandingPagemodularTestUnionConnectInput","kind":"INPUT_OBJECT"},{"name":"LandingPagemodularTestUnionCreateInput","kind":"INPUT_OBJECT"},{"name":"LandingPagemodularTestUnionCreateManyInlineInput","kind":"INPUT_OBJECT"},{"name":"LandingPagemodularTestUnionCreateOneInlineInput","kind":"INPUT_OBJECT"},{"name":"LandingPagemodularTestUnionCreateWithPositionInput","kind":"INPUT_OBJECT"},{"name":"LandingPagemodularTestUnionUpdateInput","kind":"INPUT_OBJECT"},{"name":"LandingPagemodularTestUnionUpdateManyInlineInput","kind":"INPUT_OBJECT"},{"name":"LandingPagemodularTestUnionUpdateManyWithNestedWhereInput","kind":"INPUT_OBJECT"},{"name":"LandingPagemodularTestUnionUpdateOneInlineInput","kind":"INPUT_OBJECT"},{"name":"LandingPagemodularTestUnionUpdateWithNestedWhereUniqueAndPositionInput","kind":"INPUT_OBJECT"},{"name":"LandingPagemodularTestUnionUpdateWithNestedWhereUniqueInput","kind":"INPUT_OBJECT"},{"name":"LandingPagemodularTestUnionUpsertWithNestedWhereUniqueAndPositionInput","kind":"INPUT_OBJECT"},{"name":"LandingPagemodularTestUnionUpsertWithNestedWhereUniqueInput","kind":"INPUT_OBJECT"},{"name":"LandingPagemodularTestUnionWhereInput","kind":"INPUT_OBJECT"},{"name":"LandingPagemodularTestUnionWhereUniqueInput","kind":"INPUT_OBJECT"},{"name":"LandingPagesectionsUnion","kind":"UNION"},{"name":"LandingPagesectionsUnionConnectInput","kind":"INPUT_OBJECT"},{"name":"LandingPagesectionsUnionCreateInput","kind":"INPUT_OBJECT"},{"name":"LandingPagesectionsUnionCreateManyInlineInput","kind":"INPUT_OBJECT"},{"name":"LandingPagesectionsUnionCreateOneInlineInput","kind":"INPUT_OBJECT"},{"name":"LandingPagesectionsUnionCreateWithPositionInput","kind":"INPUT_OBJECT"},{"name":"LandingPagesectionsUnionUpdateInput","kind":"INPUT_OBJECT"},{"name":"LandingPagesectionsUnionUpdateManyInlineInput","kind":"INPUT_OBJECT"},{"name":"LandingPagesectionsUnionUpdateManyWithNestedWhereInput","kind":"INPUT_OBJECT"},{"name":"LandingPagesectionsUnionUpdateOneInlineInput","kind":"INPUT_OBJECT"},{"name":"LandingPagesectionsUnionUpdateWithNestedWhereUniqueAndPositionInput","kind":"INPUT_OBJECT"},{"name":"LandingPagesectionsUnionUpdateWithNestedWhereUniqueInput","kind":"INPUT_OBJECT"},{"name":"LandingPagesectionsUnionUpsertWithNestedWhereUniqueAndPositionInput","kind":"INPUT_OBJECT"},{"name":"LandingPagesectionsUnionUpsertWithNestedWhereUniqueInput","kind":"INPUT_OBJECT"},{"name":"LandingPagesectionsUnionWhereInput","kind":"INPUT_OBJECT"},{"name":"LandingPagesectionsUnionWhereUniqueInput","kind":"INPUT_OBJECT"},{"name":"Link","kind":"OBJECT"},{"name":"LinkConnectInput","kind":"INPUT_OBJECT"},{"name":"LinkConnection","kind":"OBJECT"},{"name":"LinkCreateInput","kind":"INPUT_OBJECT"},{"name":"LinkCreateLocalizationDataInput","kind":"INPUT_OBJECT"},{"name":"LinkCreateLocalizationInput","kind":"INPUT_OBJECT"},{"name":"LinkCreateLocalizationsInput","kind":"INPUT_OBJECT"},{"name":"LinkCreateManyInlineInput","kind":"INPUT_OBJECT"},{"name":"LinkCreateOneInlineInput","kind":"INPUT_OBJECT"},{"name":"LinkCreateWithPositionInput","kind":"INPUT_OBJECT"},{"name":"LinkEdge","kind":"OBJECT"},{"name":"LinkManyWhereInput","kind":"INPUT_OBJECT"},{"name":"LinkOrderByInput","kind":"ENUM"},{"name":"LinkParent","kind":"UNION"},{"name":"LinkParentConnectInput","kind":"INPUT_OBJECT"},{"name":"LinkParentCreateInput","kind":"INPUT_OBJECT"},{"name":"LinkParentCreateManyInlineInput","kind":"INPUT_OBJECT"},{"name":"LinkParentCreateOneInlineInput","kind":"INPUT_OBJECT"},{"name":"LinkParentUpdateInput","kind":"INPUT_OBJECT"},{"name":"LinkParentUpdateManyInlineInput","kind":"INPUT_OBJECT"},{"name":"LinkParentUpdateManyWithNestedWhereInput","kind":"INPUT_OBJECT"},{"name":"LinkParentUpdateOneInlineInput","kind":"INPUT_OBJECT"},{"name":"LinkParentUpdateWithNestedWhereUniqueInput","kind":"INPUT_OBJECT"},{"name":"LinkParentUpsertWithNestedWhereUniqueInput","kind":"INPUT_OBJECT"},{"name":"LinkParentWhereInput","kind":"INPUT_OBJECT"},{"name":"LinkParentWhereUniqueInput","kind":"INPUT_OBJECT"},{"name":"LinkUpdateInput","kind":"INPUT_OBJECT"},{"name":"LinkUpdateLocalizationDataInput","kind":"INPUT_OBJECT"},{"name":"LinkUpdateLocalizationInput","kind":"INPUT_OBJECT"},{"name":"LinkUpdateLocalizationsInput","kind":"INPUT_OBJECT"},{"name":"LinkUpdateManyInlineInput","kind":"INPUT_OBJECT"},{"name":"LinkUpdateManyInput","kind":"INPUT_OBJECT"},{"name":"LinkUpdateManyLocalizationDataInput","kind":"INPUT_OBJECT"},{"name":"LinkUpdateManyLocalizationInput","kind":"INPUT_OBJECT"},{"name":"LinkUpdateManyLocalizationsInput","kind":"INPUT_OBJECT"},{"name":"LinkUpdateManyWithNestedWhereInput","kind":"INPUT_OBJECT"},{"name":"LinkUpdateOneInlineInput","kind":"INPUT_OBJECT"},{"name":"LinkUpdateWithNestedWhereUniqueAndPositionInput","kind":"INPUT_OBJECT"},{"name":"LinkUpdateWithNestedWhereUniqueInput","kind":"INPUT_OBJECT"},{"name":"LinkUpsertInput","kind":"INPUT_OBJECT"},{"name":"LinkUpsertLocalizationInput","kind":"INPUT_OBJECT"},{"name":"LinkUpsertWithNestedWhereUniqueAndPositionInput","kind":"INPUT_OBJECT"},{"name":"LinkUpsertWithNestedWhereUniqueInput","kind":"INPUT_OBJECT"},{"name":"LinkWhereInput","kind":"INPUT_OBJECT"},{"name":"LinkWhereUniqueInput","kind":"INPUT_OBJECT"},{"name":"Locale","kind":"ENUM"},{"name":"Location","kind":"OBJECT"},{"name":"LocationInput","kind":"INPUT_OBJECT"},{"name":"Long","kind":"SCALAR"},{"name":"Mutation","kind":"OBJECT"},{"name":"NavItem","kind":"OBJECT"},{"name":"NavItemConnectInput","kind":"INPUT_OBJECT"},{"name":"NavItemConnection","kind":"OBJECT"},{"name":"NavItemCreateInput","kind":"INPUT_OBJECT"},{"name":"NavItemCreateLocalizationDataInput","kind":"INPUT_OBJECT"},{"name":"NavItemCreateLocalizationInput","kind":"INPUT_OBJECT"},{"name":"NavItemCreateLocalizationsInput","kind":"INPUT_OBJECT"},{"name":"NavItemCreateManyInlineInput","kind":"INPUT_OBJECT"},{"name":"NavItemCreateOneInlineInput","kind":"INPUT_OBJECT"},{"name":"NavItemCreateWithPositionInput","kind":"INPUT_OBJECT"},{"name":"NavItemEdge","kind":"OBJECT"},{"name":"NavItemManyWhereInput","kind":"INPUT_OBJECT"},{"name":"NavItemOrderByInput","kind":"ENUM"},{"name":"NavItemParent","kind":"UNION"},{"name":"NavItemParentConnectInput","kind":"INPUT_OBJECT"},{"name":"NavItemParentCreateInput","kind":"INPUT_OBJECT"},{"name":"NavItemParentCreateManyInlineInput","kind":"INPUT_OBJECT"},{"name":"NavItemParentCreateOneInlineInput","kind":"INPUT_OBJECT"},{"name":"NavItemParentUpdateInput","kind":"INPUT_OBJECT"},{"name":"NavItemParentUpdateManyInlineInput","kind":"INPUT_OBJECT"},{"name":"NavItemParentUpdateManyWithNestedWhereInput","kind":"INPUT_OBJECT"},{"name":"NavItemParentUpdateOneInlineInput","kind":"INPUT_OBJECT"},{"name":"NavItemParentUpdateWithNestedWhereUniqueInput","kind":"INPUT_OBJECT"},{"name":"NavItemParentUpsertWithNestedWhereUniqueInput","kind":"INPUT_OBJECT"},{"name":"NavItemParentWhereInput","kind":"INPUT_OBJECT"},{"name":"NavItemParentWhereUniqueInput","kind":"INPUT_OBJECT"},{"name":"NavItemUpdateInput","kind":"INPUT_OBJECT"},{"name":"NavItemUpdateLocalizationDataInput","kind":"INPUT_OBJECT"},{"name":"NavItemUpdateLocalizationInput","kind":"INPUT_OBJECT"},{"name":"NavItemUpdateLocalizationsInput","kind":"INPUT_OBJECT"},{"name":"NavItemUpdateManyInlineInput","kind":"INPUT_OBJECT"},{"name":"NavItemUpdateManyInput","kind":"INPUT_OBJECT"},{"name":"NavItemUpdateManyLocalizationDataInput","kind":"INPUT_OBJECT"},{"name":"NavItemUpdateManyLocalizationInput","kind":"INPUT_OBJECT"},{"name":"NavItemUpdateManyLocalizationsInput","kind":"INPUT_OBJECT"},{"name":"NavItemUpdateManyWithNestedWhereInput","kind":"INPUT_OBJECT"},{"name":"NavItemUpdateOneInlineInput","kind":"INPUT_OBJECT"},{"name":"NavItemUpdateWithNestedWhereUniqueAndPositionInput","kind":"INPUT_OBJECT"},{"name":"NavItemUpdateWithNestedWhereUniqueInput","kind":"INPUT_OBJECT"},{"name":"NavItemUpsertInput","kind":"INPUT_OBJECT"},{"name":"NavItemUpsertLocalizationInput","kind":"INPUT_OBJECT"},{"name":"NavItemUpsertWithNestedWhereUniqueAndPositionInput","kind":"INPUT_OBJECT"},{"name":"NavItemUpsertWithNestedWhereUniqueInput","kind":"INPUT_OBJECT"},{"name":"NavItemWhereInput","kind":"INPUT_OBJECT"},{"name":"NavItemWhereUniqueInput","kind":"INPUT_OBJECT"},{"name":"NavItemmulitpleLinksUnion","kind":"UNION"},{"name":"NavItemmulitpleLinksUnionConnectInput","kind":"INPUT_OBJECT"},{"name":"NavItemmulitpleLinksUnionCreateInput","kind":"INPUT_OBJECT"},{"name":"NavItemmulitpleLinksUnionCreateManyInlineInput","kind":"INPUT_OBJECT"},{"name":"NavItemmulitpleLinksUnionCreateOneInlineInput","kind":"INPUT_OBJECT"},{"name":"NavItemmulitpleLinksUnionCreateWithPositionInput","kind":"INPUT_OBJECT"},{"name":"NavItemmulitpleLinksUnionUpdateInput","kind":"INPUT_OBJECT"},{"name":"NavItemmulitpleLinksUnionUpdateManyInlineInput","kind":"INPUT_OBJECT"},{"name":"NavItemmulitpleLinksUnionUpdateManyWithNestedWhereInput","kind":"INPUT_OBJECT"},{"name":"NavItemmulitpleLinksUnionUpdateOneInlineInput","kind":"INPUT_OBJECT"},{"name":"NavItemmulitpleLinksUnionUpdateWithNestedWhereUniqueAndPositionInput","kind":"INPUT_OBJECT"},{"name":"NavItemmulitpleLinksUnionUpdateWithNestedWhereUniqueInput","kind":"INPUT_OBJECT"},{"name":"NavItemmulitpleLinksUnionUpsertWithNestedWhereUniqueAndPositionInput","kind":"INPUT_OBJECT"},{"name":"NavItemmulitpleLinksUnionUpsertWithNestedWhereUniqueInput","kind":"INPUT_OBJECT"},{"name":"NavItemmulitpleLinksUnionWhereInput","kind":"INPUT_OBJECT"},{"name":"NavItemmulitpleLinksUnionWhereUniqueInput","kind":"INPUT_OBJECT"},{"name":"Navigation","kind":"OBJECT"},{"name":"NavigationConnectInput","kind":"INPUT_OBJECT"},{"name":"NavigationConnection","kind":"OBJECT"},{"name":"NavigationCreateInput","kind":"INPUT_OBJECT"},{"name":"NavigationCreateLocalizationDataInput","kind":"INPUT_OBJECT"},{"name":"NavigationCreateLocalizationInput","kind":"INPUT_OBJECT"},{"name":"NavigationCreateLocalizationsInput","kind":"INPUT_OBJECT"},{"name":"NavigationCreateManyInlineInput","kind":"INPUT_OBJECT"},{"name":"NavigationCreateOneInlineInput","kind":"INPUT_OBJECT"},{"name":"NavigationEdge","kind":"OBJECT"},{"name":"NavigationManyWhereInput","kind":"INPUT_OBJECT"},{"name":"NavigationOrderByInput","kind":"ENUM"},{"name":"NavigationUpdateInput","kind":"INPUT_OBJECT"},{"name":"NavigationUpdateLocalizationsInput","kind":"INPUT_OBJECT"},{"name":"NavigationUpdateManyInlineInput","kind":"INPUT_OBJECT"},{"name":"NavigationUpdateManyInput","kind":"INPUT_OBJECT"},{"name":"NavigationUpdateManyWithNestedWhereInput","kind":"INPUT_OBJECT"},{"name":"NavigationUpdateOneInlineInput","kind":"INPUT_OBJECT"},{"name":"NavigationUpdateWithNestedWhereUniqueInput","kind":"INPUT_OBJECT"},{"name":"NavigationUpsertInput","kind":"INPUT_OBJECT"},{"name":"NavigationUpsertWithNestedWhereUniqueInput","kind":"INPUT_OBJECT"},{"name":"NavigationWhereComparatorInput","kind":"INPUT_OBJECT"},{"name":"NavigationWhereInput","kind":"INPUT_OBJECT"},{"name":"NavigationWhereStageInput","kind":"INPUT_OBJECT"},{"name":"NavigationWhereUniqueInput","kind":"INPUT_OBJECT"},{"name":"Node","kind":"INTERFACE"},{"name":"PageInfo","kind":"OBJECT"},{"name":"Product","kind":"OBJECT"},{"name":"ProductAttributes","kind":"OBJECT"},{"name":"ProductAttributesConnectInput","kind":"INPUT_OBJECT"},{"name":"ProductAttributesConnection","kind":"OBJECT"},{"name":"ProductAttributesCreateInput","kind":"INPUT_OBJECT"},{"name":"ProductAttributesCreateManyInlineInput","kind":"INPUT_OBJECT"},{"name":"ProductAttributesCreateOneInlineInput","kind":"INPUT_OBJECT"},{"name":"ProductAttributesCreateWithPositionInput","kind":"INPUT_OBJECT"},{"name":"ProductAttributesEdge","kind":"OBJECT"},{"name":"ProductAttributesManyWhereInput","kind":"INPUT_OBJECT"},{"name":"ProductAttributesOrderByInput","kind":"ENUM"},{"name":"ProductAttributesParent","kind":"UNION"},{"name":"ProductAttributesParentConnectInput","kind":"INPUT_OBJECT"},{"name":"ProductAttributesParentCreateInput","kind":"INPUT_OBJECT"},{"name":"ProductAttributesParentCreateManyInlineInput","kind":"INPUT_OBJECT"},{"name":"ProductAttributesParentCreateOneInlineInput","kind":"INPUT_OBJECT"},{"name":"ProductAttributesParentUpdateInput","kind":"INPUT_OBJECT"},{"name":"ProductAttributesParentUpdateManyInlineInput","kind":"INPUT_OBJECT"},{"name":"ProductAttributesParentUpdateManyWithNestedWhereInput","kind":"INPUT_OBJECT"},{"name":"ProductAttributesParentUpdateOneInlineInput","kind":"INPUT_OBJECT"},{"name":"ProductAttributesParentUpdateWithNestedWhereUniqueInput","kind":"INPUT_OBJECT"},{"name":"ProductAttributesParentUpsertWithNestedWhereUniqueInput","kind":"INPUT_OBJECT"},{"name":"ProductAttributesParentWhereInput","kind":"INPUT_OBJECT"},{"name":"ProductAttributesParentWhereUniqueInput","kind":"INPUT_OBJECT"},{"name":"ProductAttributesUpdateInput","kind":"INPUT_OBJECT"},{"name":"ProductAttributesUpdateManyInlineInput","kind":"INPUT_OBJECT"},{"name":"ProductAttributesUpdateManyInput","kind":"INPUT_OBJECT"},{"name":"ProductAttributesUpdateManyWithNestedWhereInput","kind":"INPUT_OBJECT"},{"name":"ProductAttributesUpdateOneInlineInput","kind":"INPUT_OBJECT"},{"name":"ProductAttributesUpdateWithNestedWhereUniqueAndPositionInput","kind":"INPUT_OBJECT"},{"name":"ProductAttributesUpdateWithNestedWhereUniqueInput","kind":"INPUT_OBJECT"},{"name":"ProductAttributesUpsertInput","kind":"INPUT_OBJECT"},{"name":"ProductAttributesUpsertWithNestedWhereUniqueAndPositionInput","kind":"INPUT_OBJECT"},{"name":"ProductAttributesUpsertWithNestedWhereUniqueInput","kind":"INPUT_OBJECT"},{"name":"ProductAttributesWhereInput","kind":"INPUT_OBJECT"},{"name":"ProductAttributesWhereUniqueInput","kind":"INPUT_OBJECT"},{"name":"ProductCategory","kind":"OBJECT"},{"name":"ProductCategoryConnectInput","kind":"INPUT_OBJECT"},{"name":"ProductCategoryConnection","kind":"OBJECT"},{"name":"ProductCategoryCreateInput","kind":"INPUT_OBJECT"},{"name":"ProductCategoryCreateLocalizationDataInput","kind":"INPUT_OBJECT"},{"name":"ProductCategoryCreateLocalizationInput","kind":"INPUT_OBJECT"},{"name":"ProductCategoryCreateLocalizationsInput","kind":"INPUT_OBJECT"},{"name":"ProductCategoryCreateManyInlineInput","kind":"INPUT_OBJECT"},{"name":"ProductCategoryCreateOneInlineInput","kind":"INPUT_OBJECT"},{"name":"ProductCategoryEdge","kind":"OBJECT"},{"name":"ProductCategoryManyWhereInput","kind":"INPUT_OBJECT"},{"name":"ProductCategoryOrderByInput","kind":"ENUM"},{"name":"ProductCategoryUpdateInput","kind":"INPUT_OBJECT"},{"name":"ProductCategoryUpdateLocalizationDataInput","kind":"INPUT_OBJECT"},{"name":"ProductCategoryUpdateLocalizationInput","kind":"INPUT_OBJECT"},{"name":"ProductCategoryUpdateLocalizationsInput","kind":"INPUT_OBJECT"},{"name":"ProductCategoryUpdateManyInlineInput","kind":"INPUT_OBJECT"},{"name":"ProductCategoryUpdateManyInput","kind":"INPUT_OBJECT"},{"name":"ProductCategoryUpdateManyLocalizationDataInput","kind":"INPUT_OBJECT"},{"name":"ProductCategoryUpdateManyLocalizationInput","kind":"INPUT_OBJECT"},{"name":"ProductCategoryUpdateManyLocalizationsInput","kind":"INPUT_OBJECT"},{"name":"ProductCategoryUpdateManyWithNestedWhereInput","kind":"INPUT_OBJECT"},{"name":"ProductCategoryUpdateOneInlineInput","kind":"INPUT_OBJECT"},{"name":"ProductCategoryUpdateWithNestedWhereUniqueInput","kind":"INPUT_OBJECT"},{"name":"ProductCategoryUpsertInput","kind":"INPUT_OBJECT"},{"name":"ProductCategoryUpsertLocalizationInput","kind":"INPUT_OBJECT"},{"name":"ProductCategoryUpsertWithNestedWhereUniqueInput","kind":"INPUT_OBJECT"},{"name":"ProductCategoryWhereComparatorInput","kind":"INPUT_OBJECT"},{"name":"ProductCategoryWhereInput","kind":"INPUT_OBJECT"},{"name":"ProductCategoryWhereStageInput","kind":"INPUT_OBJECT"},{"name":"ProductCategoryWhereUniqueInput","kind":"INPUT_OBJECT"},{"name":"ProductColor","kind":"ENUM"},{"name":"ProductConnectInput","kind":"INPUT_OBJECT"},{"name":"ProductConnection","kind":"OBJECT"},{"name":"ProductCreateInput","kind":"INPUT_OBJECT"},{"name":"ProductCreateLocalizationDataInput","kind":"INPUT_OBJECT"},{"name":"ProductCreateLocalizationInput","kind":"INPUT_OBJECT"},{"name":"ProductCreateLocalizationsInput","kind":"INPUT_OBJECT"},{"name":"ProductCreateManyInlineInput","kind":"INPUT_OBJECT"},{"name":"ProductCreateOneInlineInput","kind":"INPUT_OBJECT"},{"name":"ProductEdge","kind":"OBJECT"},{"name":"ProductGrid","kind":"OBJECT"},{"name":"ProductGridConnectInput","kind":"INPUT_OBJECT"},{"name":"ProductGridConnection","kind":"OBJECT"},{"name":"ProductGridCreateInput","kind":"INPUT_OBJECT"},{"name":"ProductGridCreateLocalizationDataInput","kind":"INPUT_OBJECT"},{"name":"ProductGridCreateLocalizationInput","kind":"INPUT_OBJECT"},{"name":"ProductGridCreateLocalizationsInput","kind":"INPUT_OBJECT"},{"name":"ProductGridCreateManyInlineInput","kind":"INPUT_OBJECT"},{"name":"ProductGridCreateOneInlineInput","kind":"INPUT_OBJECT"},{"name":"ProductGridCreateWithPositionInput","kind":"INPUT_OBJECT"},{"name":"ProductGridEdge","kind":"OBJECT"},{"name":"ProductGridManyWhereInput","kind":"INPUT_OBJECT"},{"name":"ProductGridOrderByInput","kind":"ENUM"},{"name":"ProductGridParent","kind":"UNION"},{"name":"ProductGridParentConnectInput","kind":"INPUT_OBJECT"},{"name":"ProductGridParentCreateInput","kind":"INPUT_OBJECT"},{"name":"ProductGridParentCreateManyInlineInput","kind":"INPUT_OBJECT"},{"name":"ProductGridParentCreateOneInlineInput","kind":"INPUT_OBJECT"},{"name":"ProductGridParentUpdateInput","kind":"INPUT_OBJECT"},{"name":"ProductGridParentUpdateManyInlineInput","kind":"INPUT_OBJECT"},{"name":"ProductGridParentUpdateManyWithNestedWhereInput","kind":"INPUT_OBJECT"},{"name":"ProductGridParentUpdateOneInlineInput","kind":"INPUT_OBJECT"},{"name":"ProductGridParentUpdateWithNestedWhereUniqueInput","kind":"INPUT_OBJECT"},{"name":"ProductGridParentUpsertWithNestedWhereUniqueInput","kind":"INPUT_OBJECT"},{"name":"ProductGridParentWhereInput","kind":"INPUT_OBJECT"},{"name":"ProductGridParentWhereUniqueInput","kind":"INPUT_OBJECT"},{"name":"ProductGridUpdateInput","kind":"INPUT_OBJECT"},{"name":"ProductGridUpdateLocalizationDataInput","kind":"INPUT_OBJECT"},{"name":"ProductGridUpdateLocalizationInput","kind":"INPUT_OBJECT"},{"name":"ProductGridUpdateLocalizationsInput","kind":"INPUT_OBJECT"},{"name":"ProductGridUpdateManyInlineInput","kind":"INPUT_OBJECT"},{"name":"ProductGridUpdateManyInput","kind":"INPUT_OBJECT"},{"name":"ProductGridUpdateManyLocalizationDataInput","kind":"INPUT_OBJECT"},{"name":"ProductGridUpdateManyLocalizationInput","kind":"INPUT_OBJECT"},{"name":"ProductGridUpdateManyLocalizationsInput","kind":"INPUT_OBJECT"},{"name":"ProductGridUpdateManyWithNestedWhereInput","kind":"INPUT_OBJECT"},{"name":"ProductGridUpdateOneInlineInput","kind":"INPUT_OBJECT"},{"name":"ProductGridUpdateWithNestedWhereUniqueAndPositionInput","kind":"INPUT_OBJECT"},{"name":"ProductGridUpdateWithNestedWhereUniqueInput","kind":"INPUT_OBJECT"},{"name":"ProductGridUpsertInput","kind":"INPUT_OBJECT"},{"name":"ProductGridUpsertLocalizationInput","kind":"INPUT_OBJECT"},{"name":"ProductGridUpsertWithNestedWhereUniqueAndPositionInput","kind":"INPUT_OBJECT"},{"name":"ProductGridUpsertWithNestedWhereUniqueInput","kind":"INPUT_OBJECT"},{"name":"ProductGridWhereInput","kind":"INPUT_OBJECT"},{"name":"ProductGridWhereUniqueInput","kind":"INPUT_OBJECT"},{"name":"ProductManyWhereInput","kind":"INPUT_OBJECT"},{"name":"ProductOrderByInput","kind":"ENUM"},{"name":"ProductPrice","kind":"OBJECT"},{"name":"ProductPriceConnectInput","kind":"INPUT_OBJECT"},{"name":"ProductPriceConnection","kind":"OBJECT"},{"name":"ProductPriceCreateInput","kind":"INPUT_OBJECT"},{"name":"ProductPriceCreateManyInlineInput","kind":"INPUT_OBJECT"},{"name":"ProductPriceCreateOneInlineInput","kind":"INPUT_OBJECT"},{"name":"ProductPriceCreateWithPositionInput","kind":"INPUT_OBJECT"},{"name":"ProductPriceEdge","kind":"OBJECT"},{"name":"ProductPriceManyWhereInput","kind":"INPUT_OBJECT"},{"name":"ProductPriceOrderByInput","kind":"ENUM"},{"name":"ProductPriceParent","kind":"UNION"},{"name":"ProductPriceParentConnectInput","kind":"INPUT_OBJECT"},{"name":"ProductPriceParentCreateInput","kind":"INPUT_OBJECT"},{"name":"ProductPriceParentCreateManyInlineInput","kind":"INPUT_OBJECT"},{"name":"ProductPriceParentCreateOneInlineInput","kind":"INPUT_OBJECT"},{"name":"ProductPriceParentUpdateInput","kind":"INPUT_OBJECT"},{"name":"ProductPriceParentUpdateManyInlineInput","kind":"INPUT_OBJECT"},{"name":"ProductPriceParentUpdateManyWithNestedWhereInput","kind":"INPUT_OBJECT"},{"name":"ProductPriceParentUpdateOneInlineInput","kind":"INPUT_OBJECT"},{"name":"ProductPriceParentUpdateWithNestedWhereUniqueInput","kind":"INPUT_OBJECT"},{"name":"ProductPriceParentUpsertWithNestedWhereUniqueInput","kind":"INPUT_OBJECT"},{"name":"ProductPriceParentWhereInput","kind":"INPUT_OBJECT"},{"name":"ProductPriceParentWhereUniqueInput","kind":"INPUT_OBJECT"},{"name":"ProductPriceUpdateInput","kind":"INPUT_OBJECT"},{"name":"ProductPriceUpdateManyInlineInput","kind":"INPUT_OBJECT"},{"name":"ProductPriceUpdateManyInput","kind":"INPUT_OBJECT"},{"name":"ProductPriceUpdateManyWithNestedWhereInput","kind":"INPUT_OBJECT"},{"name":"ProductPriceUpdateOneInlineInput","kind":"INPUT_OBJECT"},{"name":"ProductPriceUpdateWithNestedWhereUniqueAndPositionInput","kind":"INPUT_OBJECT"},{"name":"ProductPriceUpdateWithNestedWhereUniqueInput","kind":"INPUT_OBJECT"},{"name":"ProductPriceUpsertInput","kind":"INPUT_OBJECT"},{"name":"ProductPriceUpsertWithNestedWhereUniqueAndPositionInput","kind":"INPUT_OBJECT"},{"name":"ProductPriceUpsertWithNestedWhereUniqueInput","kind":"INPUT_OBJECT"},{"name":"ProductPriceWhereInput","kind":"INPUT_OBJECT"},{"name":"ProductPriceWhereUniqueInput","kind":"INPUT_OBJECT"},{"name":"ProductProductDescriptionRichText","kind":"OBJECT"},{"name":"ProductProductDescriptionRichTextEmbeddedTypes","kind":"UNION"},{"name":"ProductReviews","kind":"OBJECT"},{"name":"ProductReviewsConnectInput","kind":"INPUT_OBJECT"},{"name":"ProductReviewsConnection","kind":"OBJECT"},{"name":"ProductReviewsCreateInput","kind":"INPUT_OBJECT"},{"name":"ProductReviewsCreateLocalizationDataInput","kind":"INPUT_OBJECT"},{"name":"ProductReviewsCreateLocalizationInput","kind":"INPUT_OBJECT"},{"name":"ProductReviewsCreateLocalizationsInput","kind":"INPUT_OBJECT"},{"name":"ProductReviewsCreateManyInlineInput","kind":"INPUT_OBJECT"},{"name":"ProductReviewsCreateOneInlineInput","kind":"INPUT_OBJECT"},{"name":"ProductReviewsEdge","kind":"OBJECT"},{"name":"ProductReviewsManyWhereInput","kind":"INPUT_OBJECT"},{"name":"ProductReviewsOrderByInput","kind":"ENUM"},{"name":"ProductReviewsUpdateInput","kind":"INPUT_OBJECT"},{"name":"ProductReviewsUpdateLocalizationDataInput","kind":"INPUT_OBJECT"},{"name":"ProductReviewsUpdateLocalizationInput","kind":"INPUT_OBJECT"},{"name":"ProductReviewsUpdateLocalizationsInput","kind":"INPUT_OBJECT"},{"name":"ProductReviewsUpdateManyInlineInput","kind":"INPUT_OBJECT"},{"name":"ProductReviewsUpdateManyInput","kind":"INPUT_OBJECT"},{"name":"ProductReviewsUpdateManyLocalizationDataInput","kind":"INPUT_OBJECT"},{"name":"ProductReviewsUpdateManyLocalizationInput","kind":"INPUT_OBJECT"},{"name":"ProductReviewsUpdateManyLocalizationsInput","kind":"INPUT_OBJECT"},{"name":"ProductReviewsUpdateManyWithNestedWhereInput","kind":"INPUT_OBJECT"},{"name":"ProductReviewsUpdateOneInlineInput","kind":"INPUT_OBJECT"},{"name":"ProductReviewsUpdateWithNestedWhereUniqueInput","kind":"INPUT_OBJECT"},{"name":"ProductReviewsUpsertInput","kind":"INPUT_OBJECT"},{"name":"ProductReviewsUpsertLocalizationInput","kind":"INPUT_OBJECT"},{"name":"ProductReviewsUpsertWithNestedWhereUniqueInput","kind":"INPUT_OBJECT"},{"name":"ProductReviewsWhereComparatorInput","kind":"INPUT_OBJECT"},{"name":"ProductReviewsWhereInput","kind":"INPUT_OBJECT"},{"name":"ProductReviewsWhereStageInput","kind":"INPUT_OBJECT"},{"name":"ProductReviewsWhereUniqueInput","kind":"INPUT_OBJECT"},{"name":"ProductSeller","kind":"OBJECT"},{"name":"ProductSellerConnectInput","kind":"INPUT_OBJECT"},{"name":"ProductSellerConnection","kind":"OBJECT"},{"name":"ProductSellerCreateInput","kind":"INPUT_OBJECT"},{"name":"ProductSellerCreateLocalizationDataInput","kind":"INPUT_OBJECT"},{"name":"ProductSellerCreateLocalizationInput","kind":"INPUT_OBJECT"},{"name":"ProductSellerCreateLocalizationsInput","kind":"INPUT_OBJECT"},{"name":"ProductSellerCreateManyInlineInput","kind":"INPUT_OBJECT"},{"name":"ProductSellerCreateOneInlineInput","kind":"INPUT_OBJECT"},{"name":"ProductSellerEdge","kind":"OBJECT"},{"name":"ProductSellerManyWhereInput","kind":"INPUT_OBJECT"},{"name":"ProductSellerOrderByInput","kind":"ENUM"},{"name":"ProductSellerUpdateInput","kind":"INPUT_OBJECT"},{"name":"ProductSellerUpdateLocalizationDataInput","kind":"INPUT_OBJECT"},{"name":"ProductSellerUpdateLocalizationInput","kind":"INPUT_OBJECT"},{"name":"ProductSellerUpdateLocalizationsInput","kind":"INPUT_OBJECT"},{"name":"ProductSellerUpdateManyInlineInput","kind":"INPUT_OBJECT"},{"name":"ProductSellerUpdateManyInput","kind":"INPUT_OBJECT"},{"name":"ProductSellerUpdateManyLocalizationDataInput","kind":"INPUT_OBJECT"},{"name":"ProductSellerUpdateManyLocalizationInput","kind":"INPUT_OBJECT"},{"name":"ProductSellerUpdateManyLocalizationsInput","kind":"INPUT_OBJECT"},{"name":"ProductSellerUpdateManyWithNestedWhereInput","kind":"INPUT_OBJECT"},{"name":"ProductSellerUpdateOneInlineInput","kind":"INPUT_OBJECT"},{"name":"ProductSellerUpdateWithNestedWhereUniqueInput","kind":"INPUT_OBJECT"},{"name":"ProductSellerUpsertInput","kind":"INPUT_OBJECT"},{"name":"ProductSellerUpsertLocalizationInput","kind":"INPUT_OBJECT"},{"name":"ProductSellerUpsertWithNestedWhereUniqueInput","kind":"INPUT_OBJECT"},{"name":"ProductSellerWhereComparatorInput","kind":"INPUT_OBJECT"},{"name":"ProductSellerWhereInput","kind":"INPUT_OBJECT"},{"name":"ProductSellerWhereStageInput","kind":"INPUT_OBJECT"},{"name":"ProductSellerWhereUniqueInput","kind":"INPUT_OBJECT"},{"name":"ProductStatus","kind":"ENUM"},{"name":"ProductTaxonomy","kind":"OBJECT"},{"name":"ProductTaxonomyConnectInput","kind":"INPUT_OBJECT"},{"name":"ProductTaxonomyConnection","kind":"OBJECT"},{"name":"ProductTaxonomyCreateInput","kind":"INPUT_OBJECT"},{"name":"ProductTaxonomyCreateManyInlineInput","kind":"INPUT_OBJECT"},{"name":"ProductTaxonomyCreateOneInlineInput","kind":"INPUT_OBJECT"},{"name":"ProductTaxonomyEdge","kind":"OBJECT"},{"name":"ProductTaxonomyManyWhereInput","kind":"INPUT_OBJECT"},{"name":"ProductTaxonomyOrderByInput","kind":"ENUM"},{"name":"ProductTaxonomyUpdateInput","kind":"INPUT_OBJECT"},{"name":"ProductTaxonomyUpdateManyInlineInput","kind":"INPUT_OBJECT"},{"name":"ProductTaxonomyUpdateManyInput","kind":"INPUT_OBJECT"},{"name":"ProductTaxonomyUpdateManyWithNestedWhereInput","kind":"INPUT_OBJECT"},{"name":"ProductTaxonomyUpdateOneInlineInput","kind":"INPUT_OBJECT"},{"name":"ProductTaxonomyUpdateWithNestedWhereUniqueInput","kind":"INPUT_OBJECT"},{"name":"ProductTaxonomyUpsertInput","kind":"INPUT_OBJECT"},{"name":"ProductTaxonomyUpsertWithNestedWhereUniqueInput","kind":"INPUT_OBJECT"},{"name":"ProductTaxonomyWhereComparatorInput","kind":"INPUT_OBJECT"},{"name":"ProductTaxonomyWhereInput","kind":"INPUT_OBJECT"},{"name":"ProductTaxonomyWhereStageInput","kind":"INPUT_OBJECT"},{"name":"ProductTaxonomyWhereUniqueInput","kind":"INPUT_OBJECT"},{"name":"ProductUpdateInput","kind":"INPUT_OBJECT"},{"name":"ProductUpdateLocalizationDataInput","kind":"INPUT_OBJECT"},{"name":"ProductUpdateLocalizationInput","kind":"INPUT_OBJECT"},{"name":"ProductUpdateLocalizationsInput","kind":"INPUT_OBJECT"},{"name":"ProductUpdateManyInlineInput","kind":"INPUT_OBJECT"},{"name":"ProductUpdateManyInput","kind":"INPUT_OBJECT"},{"name":"ProductUpdateManyLocalizationDataInput","kind":"INPUT_OBJECT"},{"name":"ProductUpdateManyLocalizationInput","kind":"INPUT_OBJECT"},{"name":"ProductUpdateManyLocalizationsInput","kind":"INPUT_OBJECT"},{"name":"ProductUpdateManyWithNestedWhereInput","kind":"INPUT_OBJECT"},{"name":"ProductUpdateOneInlineInput","kind":"INPUT_OBJECT"},{"name":"ProductUpdateWithNestedWhereUniqueInput","kind":"INPUT_OBJECT"},{"name":"ProductUpsertInput","kind":"INPUT_OBJECT"},{"name":"ProductUpsertLocalizationInput","kind":"INPUT_OBJECT"},{"name":"ProductUpsertWithNestedWhereUniqueInput","kind":"INPUT_OBJECT"},{"name":"ProductVariant","kind":"OBJECT"},{"name":"ProductVariantConnectInput","kind":"INPUT_OBJECT"},{"name":"ProductVariantConnection","kind":"OBJECT"},{"name":"ProductVariantCreateInput","kind":"INPUT_OBJECT"},{"name":"ProductVariantCreateLocalizationDataInput","kind":"INPUT_OBJECT"},{"name":"ProductVariantCreateLocalizationInput","kind":"INPUT_OBJECT"},{"name":"ProductVariantCreateLocalizationsInput","kind":"INPUT_OBJECT"},{"name":"ProductVariantCreateManyInlineInput","kind":"INPUT_OBJECT"},{"name":"ProductVariantCreateOneInlineInput","kind":"INPUT_OBJECT"},{"name":"ProductVariantEdge","kind":"OBJECT"},{"name":"ProductVariantManyWhereInput","kind":"INPUT_OBJECT"},{"name":"ProductVariantOrderByInput","kind":"ENUM"},{"name":"ProductVariantUpdateInput","kind":"INPUT_OBJECT"},{"name":"ProductVariantUpdateLocalizationDataInput","kind":"INPUT_OBJECT"},{"name":"ProductVariantUpdateLocalizationInput","kind":"INPUT_OBJECT"},{"name":"ProductVariantUpdateLocalizationsInput","kind":"INPUT_OBJECT"},{"name":"ProductVariantUpdateManyInlineInput","kind":"INPUT_OBJECT"},{"name":"ProductVariantUpdateManyInput","kind":"INPUT_OBJECT"},{"name":"ProductVariantUpdateManyLocalizationDataInput","kind":"INPUT_OBJECT"},{"name":"ProductVariantUpdateManyLocalizationInput","kind":"INPUT_OBJECT"},{"name":"ProductVariantUpdateManyLocalizationsInput","kind":"INPUT_OBJECT"},{"name":"ProductVariantUpdateManyWithNestedWhereInput","kind":"INPUT_OBJECT"},{"name":"ProductVariantUpdateOneInlineInput","kind":"INPUT_OBJECT"},{"name":"ProductVariantUpdateWithNestedWhereUniqueInput","kind":"INPUT_OBJECT"},{"name":"ProductVariantUpsertInput","kind":"INPUT_OBJECT"},{"name":"ProductVariantUpsertLocalizationInput","kind":"INPUT_OBJECT"},{"name":"ProductVariantUpsertWithNestedWhereUniqueInput","kind":"INPUT_OBJECT"},{"name":"ProductVariantWhereComparatorInput","kind":"INPUT_OBJECT"},{"name":"ProductVariantWhereInput","kind":"INPUT_OBJECT"},{"name":"ProductVariantWhereStageInput","kind":"INPUT_OBJECT"},{"name":"ProductVariantWhereUniqueInput","kind":"INPUT_OBJECT"},{"name":"ProductWhereComparatorInput","kind":"INPUT_OBJECT"},{"name":"ProductWhereInput","kind":"INPUT_OBJECT"},{"name":"ProductWhereStageInput","kind":"INPUT_OBJECT"},{"name":"ProductWhereUniqueInput","kind":"INPUT_OBJECT"},{"name":"ProductproductVariantsUnion","kind":"UNION"},{"name":"ProductproductVariantsUnionConnectInput","kind":"INPUT_OBJECT"},{"name":"ProductproductVariantsUnionCreateInput","kind":"INPUT_OBJECT"},{"name":"ProductproductVariantsUnionCreateManyInlineInput","kind":"INPUT_OBJECT"},{"name":"ProductproductVariantsUnionCreateOneInlineInput","kind":"INPUT_OBJECT"},{"name":"ProductproductVariantsUnionCreateWithPositionInput","kind":"INPUT_OBJECT"},{"name":"ProductproductVariantsUnionUpdateInput","kind":"INPUT_OBJECT"},{"name":"ProductproductVariantsUnionUpdateManyInlineInput","kind":"INPUT_OBJECT"},{"name":"ProductproductVariantsUnionUpdateManyWithNestedWhereInput","kind":"INPUT_OBJECT"},{"name":"ProductproductVariantsUnionUpdateOneInlineInput","kind":"INPUT_OBJECT"},{"name":"ProductproductVariantsUnionUpdateWithNestedWhereUniqueAndPositionInput","kind":"INPUT_OBJECT"},{"name":"ProductproductVariantsUnionUpdateWithNestedWhereUniqueInput","kind":"INPUT_OBJECT"},{"name":"ProductproductVariantsUnionUpsertWithNestedWhereUniqueAndPositionInput","kind":"INPUT_OBJECT"},{"name":"ProductproductVariantsUnionUpsertWithNestedWhereUniqueInput","kind":"INPUT_OBJECT"},{"name":"ProductproductVariantsUnionWhereInput","kind":"INPUT_OBJECT"},{"name":"ProductproductVariantsUnionWhereUniqueInput","kind":"INPUT_OBJECT"},{"name":"PublishLocaleInput","kind":"INPUT_OBJECT"},{"name":"Query","kind":"OBJECT"},{"name":"RGBA","kind":"OBJECT"},{"name":"RGBAHue","kind":"SCALAR"},{"name":"RGBAInput","kind":"INPUT_OBJECT"},{"name":"RGBATransparency","kind":"SCALAR"},{"name":"RelatedProduct","kind":"OBJECT"},{"name":"RelatedProductConnectInput","kind":"INPUT_OBJECT"},{"name":"RelatedProductConnection","kind":"OBJECT"},{"name":"RelatedProductCreateInput","kind":"INPUT_OBJECT"},{"name":"RelatedProductCreateLocalizationDataInput","kind":"INPUT_OBJECT"},{"name":"RelatedProductCreateLocalizationInput","kind":"INPUT_OBJECT"},{"name":"RelatedProductCreateLocalizationsInput","kind":"INPUT_OBJECT"},{"name":"RelatedProductCreateManyInlineInput","kind":"INPUT_OBJECT"},{"name":"RelatedProductCreateOneInlineInput","kind":"INPUT_OBJECT"},{"name":"RelatedProductCreateWithPositionInput","kind":"INPUT_OBJECT"},{"name":"RelatedProductEdge","kind":"OBJECT"},{"name":"RelatedProductManyWhereInput","kind":"INPUT_OBJECT"},{"name":"RelatedProductOrderByInput","kind":"ENUM"},{"name":"RelatedProductParent","kind":"UNION"},{"name":"RelatedProductParentConnectInput","kind":"INPUT_OBJECT"},{"name":"RelatedProductParentCreateInput","kind":"INPUT_OBJECT"},{"name":"RelatedProductParentCreateManyInlineInput","kind":"INPUT_OBJECT"},{"name":"RelatedProductParentCreateOneInlineInput","kind":"INPUT_OBJECT"},{"name":"RelatedProductParentUpdateInput","kind":"INPUT_OBJECT"},{"name":"RelatedProductParentUpdateManyInlineInput","kind":"INPUT_OBJECT"},{"name":"RelatedProductParentUpdateManyWithNestedWhereInput","kind":"INPUT_OBJECT"},{"name":"RelatedProductParentUpdateOneInlineInput","kind":"INPUT_OBJECT"},{"name":"RelatedProductParentUpdateWithNestedWhereUniqueInput","kind":"INPUT_OBJECT"},{"name":"RelatedProductParentUpsertWithNestedWhereUniqueInput","kind":"INPUT_OBJECT"},{"name":"RelatedProductParentWhereInput","kind":"INPUT_OBJECT"},{"name":"RelatedProductParentWhereUniqueInput","kind":"INPUT_OBJECT"},{"name":"RelatedProductUpdateInput","kind":"INPUT_OBJECT"},{"name":"RelatedProductUpdateLocalizationDataInput","kind":"INPUT_OBJECT"},{"name":"RelatedProductUpdateLocalizationInput","kind":"INPUT_OBJECT"},{"name":"RelatedProductUpdateLocalizationsInput","kind":"INPUT_OBJECT"},{"name":"RelatedProductUpdateManyInlineInput","kind":"INPUT_OBJECT"},{"name":"RelatedProductUpdateManyInput","kind":"INPUT_OBJECT"},{"name":"RelatedProductUpdateManyLocalizationDataInput","kind":"INPUT_OBJECT"},{"name":"RelatedProductUpdateManyLocalizationInput","kind":"INPUT_OBJECT"},{"name":"RelatedProductUpdateManyLocalizationsInput","kind":"INPUT_OBJECT"},{"name":"RelatedProductUpdateManyWithNestedWhereInput","kind":"INPUT_OBJECT"},{"name":"RelatedProductUpdateOneInlineInput","kind":"INPUT_OBJECT"},{"name":"RelatedProductUpdateWithNestedWhereUniqueAndPositionInput","kind":"INPUT_OBJECT"},{"name":"RelatedProductUpdateWithNestedWhereUniqueInput","kind":"INPUT_OBJECT"},{"name":"RelatedProductUpsertInput","kind":"INPUT_OBJECT"},{"name":"RelatedProductUpsertLocalizationInput","kind":"INPUT_OBJECT"},{"name":"RelatedProductUpsertWithNestedWhereUniqueAndPositionInput","kind":"INPUT_OBJECT"},{"name":"RelatedProductUpsertWithNestedWhereUniqueInput","kind":"INPUT_OBJECT"},{"name":"RelatedProductWhereInput","kind":"INPUT_OBJECT"},{"name":"RelatedProductWhereUniqueInput","kind":"INPUT_OBJECT"},{"name":"RemoteReviewsSection","kind":"OBJECT"},{"name":"RemoteReviewsSectionConnectInput","kind":"INPUT_OBJECT"},{"name":"RemoteReviewsSectionConnection","kind":"OBJECT"},{"name":"RemoteReviewsSectionCreateInput","kind":"INPUT_OBJECT"},{"name":"RemoteReviewsSectionCreateLocalizationDataInput","kind":"INPUT_OBJECT"},{"name":"RemoteReviewsSectionCreateLocalizationInput","kind":"INPUT_OBJECT"},{"name":"RemoteReviewsSectionCreateLocalizationsInput","kind":"INPUT_OBJECT"},{"name":"RemoteReviewsSectionCreateManyInlineInput","kind":"INPUT_OBJECT"},{"name":"RemoteReviewsSectionCreateOneInlineInput","kind":"INPUT_OBJECT"},{"name":"RemoteReviewsSectionCreateWithPositionInput","kind":"INPUT_OBJECT"},{"name":"RemoteReviewsSectionEdge","kind":"OBJECT"},{"name":"RemoteReviewsSectionManyWhereInput","kind":"INPUT_OBJECT"},{"name":"RemoteReviewsSectionOrderByInput","kind":"ENUM"},{"name":"RemoteReviewsSectionParent","kind":"UNION"},{"name":"RemoteReviewsSectionParentConnectInput","kind":"INPUT_OBJECT"},{"name":"RemoteReviewsSectionParentCreateInput","kind":"INPUT_OBJECT"},{"name":"RemoteReviewsSectionParentCreateManyInlineInput","kind":"INPUT_OBJECT"},{"name":"RemoteReviewsSectionParentCreateOneInlineInput","kind":"INPUT_OBJECT"},{"name":"RemoteReviewsSectionParentUpdateInput","kind":"INPUT_OBJECT"},{"name":"RemoteReviewsSectionParentUpdateManyInlineInput","kind":"INPUT_OBJECT"},{"name":"RemoteReviewsSectionParentUpdateManyWithNestedWhereInput","kind":"INPUT_OBJECT"},{"name":"RemoteReviewsSectionParentUpdateOneInlineInput","kind":"INPUT_OBJECT"},{"name":"RemoteReviewsSectionParentUpdateWithNestedWhereUniqueInput","kind":"INPUT_OBJECT"},{"name":"RemoteReviewsSectionParentUpsertWithNestedWhereUniqueInput","kind":"INPUT_OBJECT"},{"name":"RemoteReviewsSectionParentWhereInput","kind":"INPUT_OBJECT"},{"name":"RemoteReviewsSectionParentWhereUniqueInput","kind":"INPUT_OBJECT"},{"name":"RemoteReviewsSectionUpdateInput","kind":"INPUT_OBJECT"},{"name":"RemoteReviewsSectionUpdateLocalizationDataInput","kind":"INPUT_OBJECT"},{"name":"RemoteReviewsSectionUpdateLocalizationInput","kind":"INPUT_OBJECT"},{"name":"RemoteReviewsSectionUpdateLocalizationsInput","kind":"INPUT_OBJECT"},{"name":"RemoteReviewsSectionUpdateManyInlineInput","kind":"INPUT_OBJECT"},{"name":"RemoteReviewsSectionUpdateManyInput","kind":"INPUT_OBJECT"},{"name":"RemoteReviewsSectionUpdateManyLocalizationDataInput","kind":"INPUT_OBJECT"},{"name":"RemoteReviewsSectionUpdateManyLocalizationInput","kind":"INPUT_OBJECT"},{"name":"RemoteReviewsSectionUpdateManyLocalizationsInput","kind":"INPUT_OBJECT"},{"name":"RemoteReviewsSectionUpdateManyWithNestedWhereInput","kind":"INPUT_OBJECT"},{"name":"RemoteReviewsSectionUpdateOneInlineInput","kind":"INPUT_OBJECT"},{"name":"RemoteReviewsSectionUpdateWithNestedWhereUniqueAndPositionInput","kind":"INPUT_OBJECT"},{"name":"RemoteReviewsSectionUpdateWithNestedWhereUniqueInput","kind":"INPUT_OBJECT"},{"name":"RemoteReviewsSectionUpsertInput","kind":"INPUT_OBJECT"},{"name":"RemoteReviewsSectionUpsertLocalizationInput","kind":"INPUT_OBJECT"},{"name":"RemoteReviewsSectionUpsertWithNestedWhereUniqueAndPositionInput","kind":"INPUT_OBJECT"},{"name":"RemoteReviewsSectionUpsertWithNestedWhereUniqueInput","kind":"INPUT_OBJECT"},{"name":"RemoteReviewsSectionWhereInput","kind":"INPUT_OBJECT"},{"name":"RemoteReviewsSectionWhereUniqueInput","kind":"INPUT_OBJECT"},{"name":"RichText","kind":"OBJECT"},{"name":"RichTextAST","kind":"SCALAR"},{"name":"ScheduledOperation","kind":"OBJECT"},{"name":"ScheduledOperationAffectedDocument","kind":"UNION"},{"name":"ScheduledOperationConnectInput","kind":"INPUT_OBJECT"},{"name":"ScheduledOperationConnection","kind":"OBJECT"},{"name":"ScheduledOperationCreateManyInlineInput","kind":"INPUT_OBJECT"},{"name":"ScheduledOperationCreateOneInlineInput","kind":"INPUT_OBJECT"},{"name":"ScheduledOperationEdge","kind":"OBJECT"},{"name":"ScheduledOperationManyWhereInput","kind":"INPUT_OBJECT"},{"name":"ScheduledOperationOrderByInput","kind":"ENUM"},{"name":"ScheduledOperationStatus","kind":"ENUM"},{"name":"ScheduledOperationUpdateManyInlineInput","kind":"INPUT_OBJECT"},{"name":"ScheduledOperationUpdateOneInlineInput","kind":"INPUT_OBJECT"},{"name":"ScheduledOperationWhereInput","kind":"INPUT_OBJECT"},{"name":"ScheduledOperationWhereUniqueInput","kind":"INPUT_OBJECT"},{"name":"ScheduledRelease","kind":"OBJECT"},{"name":"ScheduledReleaseConnectInput","kind":"INPUT_OBJECT"},{"name":"ScheduledReleaseConnection","kind":"OBJECT"},{"name":"ScheduledReleaseCreateInput","kind":"INPUT_OBJECT"},{"name":"ScheduledReleaseCreateManyInlineInput","kind":"INPUT_OBJECT"},{"name":"ScheduledReleaseCreateOneInlineInput","kind":"INPUT_OBJECT"},{"name":"ScheduledReleaseEdge","kind":"OBJECT"},{"name":"ScheduledReleaseManyWhereInput","kind":"INPUT_OBJECT"},{"name":"ScheduledReleaseOrderByInput","kind":"ENUM"},{"name":"ScheduledReleaseStatus","kind":"ENUM"},{"name":"ScheduledReleaseUpdateInput","kind":"INPUT_OBJECT"},{"name":"ScheduledReleaseUpdateManyInlineInput","kind":"INPUT_OBJECT"},{"name":"ScheduledReleaseUpdateManyInput","kind":"INPUT_OBJECT"},{"name":"ScheduledReleaseUpdateManyWithNestedWhereInput","kind":"INPUT_OBJECT"},{"name":"ScheduledReleaseUpdateOneInlineInput","kind":"INPUT_OBJECT"},{"name":"ScheduledReleaseUpdateWithNestedWhereUniqueInput","kind":"INPUT_OBJECT"},{"name":"ScheduledReleaseUpsertInput","kind":"INPUT_OBJECT"},{"name":"ScheduledReleaseUpsertWithNestedWhereUniqueInput","kind":"INPUT_OBJECT"},{"name":"ScheduledReleaseWhereInput","kind":"INPUT_OBJECT"},{"name":"ScheduledReleaseWhereUniqueInput","kind":"INPUT_OBJECT"},{"name":"Segment","kind":"OBJECT"},{"name":"SegmentConnectInput","kind":"INPUT_OBJECT"},{"name":"SegmentConnection","kind":"OBJECT"},{"name":"SegmentCreateInput","kind":"INPUT_OBJECT"},{"name":"SegmentCreateManyInlineInput","kind":"INPUT_OBJECT"},{"name":"SegmentCreateOneInlineInput","kind":"INPUT_OBJECT"},{"name":"SegmentEdge","kind":"OBJECT"},{"name":"SegmentManyWhereInput","kind":"INPUT_OBJECT"},{"name":"SegmentOrderByInput","kind":"ENUM"},{"name":"SegmentUpdateInput","kind":"INPUT_OBJECT"},{"name":"SegmentUpdateManyInlineInput","kind":"INPUT_OBJECT"},{"name":"SegmentUpdateManyInput","kind":"INPUT_OBJECT"},{"name":"SegmentUpdateManyWithNestedWhereInput","kind":"INPUT_OBJECT"},{"name":"SegmentUpdateOneInlineInput","kind":"INPUT_OBJECT"},{"name":"SegmentUpdateWithNestedWhereUniqueInput","kind":"INPUT_OBJECT"},{"name":"SegmentUpsertInput","kind":"INPUT_OBJECT"},{"name":"SegmentUpsertWithNestedWhereUniqueInput","kind":"INPUT_OBJECT"},{"name":"SegmentWhereComparatorInput","kind":"INPUT_OBJECT"},{"name":"SegmentWhereInput","kind":"INPUT_OBJECT"},{"name":"SegmentWhereStageInput","kind":"INPUT_OBJECT"},{"name":"SegmentWhereUniqueInput","kind":"INPUT_OBJECT"},{"name":"Seo","kind":"OBJECT"},{"name":"SeoConnectInput","kind":"INPUT_OBJECT"},{"name":"SeoConnection","kind":"OBJECT"},{"name":"SeoCreateInput","kind":"INPUT_OBJECT"},{"name":"SeoCreateLocalizationDataInput","kind":"INPUT_OBJECT"},{"name":"SeoCreateLocalizationInput","kind":"INPUT_OBJECT"},{"name":"SeoCreateLocalizationsInput","kind":"INPUT_OBJECT"},{"name":"SeoCreateManyInlineInput","kind":"INPUT_OBJECT"},{"name":"SeoCreateOneInlineInput","kind":"INPUT_OBJECT"},{"name":"SeoCreateWithPositionInput","kind":"INPUT_OBJECT"},{"name":"SeoEdge","kind":"OBJECT"},{"name":"SeoManyWhereInput","kind":"INPUT_OBJECT"},{"name":"SeoOrderByInput","kind":"ENUM"},{"name":"SeoParent","kind":"UNION"},{"name":"SeoParentConnectInput","kind":"INPUT_OBJECT"},{"name":"SeoParentCreateInput","kind":"INPUT_OBJECT"},{"name":"SeoParentCreateManyInlineInput","kind":"INPUT_OBJECT"},{"name":"SeoParentCreateOneInlineInput","kind":"INPUT_OBJECT"},{"name":"SeoParentUpdateInput","kind":"INPUT_OBJECT"},{"name":"SeoParentUpdateManyInlineInput","kind":"INPUT_OBJECT"},{"name":"SeoParentUpdateManyWithNestedWhereInput","kind":"INPUT_OBJECT"},{"name":"SeoParentUpdateOneInlineInput","kind":"INPUT_OBJECT"},{"name":"SeoParentUpdateWithNestedWhereUniqueInput","kind":"INPUT_OBJECT"},{"name":"SeoParentUpsertWithNestedWhereUniqueInput","kind":"INPUT_OBJECT"},{"name":"SeoParentWhereInput","kind":"INPUT_OBJECT"},{"name":"SeoParentWhereUniqueInput","kind":"INPUT_OBJECT"},{"name":"SeoUpdateInput","kind":"INPUT_OBJECT"},{"name":"SeoUpdateLocalizationDataInput","kind":"INPUT_OBJECT"},{"name":"SeoUpdateLocalizationInput","kind":"INPUT_OBJECT"},{"name":"SeoUpdateLocalizationsInput","kind":"INPUT_OBJECT"},{"name":"SeoUpdateManyInlineInput","kind":"INPUT_OBJECT"},{"name":"SeoUpdateManyInput","kind":"INPUT_OBJECT"},{"name":"SeoUpdateManyLocalizationDataInput","kind":"INPUT_OBJECT"},{"name":"SeoUpdateManyLocalizationInput","kind":"INPUT_OBJECT"},{"name":"SeoUpdateManyLocalizationsInput","kind":"INPUT_OBJECT"},{"name":"SeoUpdateManyWithNestedWhereInput","kind":"INPUT_OBJECT"},{"name":"SeoUpdateOneInlineInput","kind":"INPUT_OBJECT"},{"name":"SeoUpdateWithNestedWhereUniqueAndPositionInput","kind":"INPUT_OBJECT"},{"name":"SeoUpdateWithNestedWhereUniqueInput","kind":"INPUT_OBJECT"},{"name":"SeoUpsertInput","kind":"INPUT_OBJECT"},{"name":"SeoUpsertLocalizationInput","kind":"INPUT_OBJECT"},{"name":"SeoUpsertWithNestedWhereUniqueAndPositionInput","kind":"INPUT_OBJECT"},{"name":"SeoUpsertWithNestedWhereUniqueInput","kind":"INPUT_OBJECT"},{"name":"SeoWhereInput","kind":"INPUT_OBJECT"},{"name":"SeoWhereUniqueInput","kind":"INPUT_OBJECT"},{"name":"ShoesSize","kind":"ENUM"},{"name":"ShoesVariant","kind":"OBJECT"},{"name":"ShoesVariantConnectInput","kind":"INPUT_OBJECT"},{"name":"ShoesVariantConnection","kind":"OBJECT"},{"name":"ShoesVariantCreateInput","kind":"INPUT_OBJECT"},{"name":"ShoesVariantCreateLocalizationDataInput","kind":"INPUT_OBJECT"},{"name":"ShoesVariantCreateLocalizationInput","kind":"INPUT_OBJECT"},{"name":"ShoesVariantCreateLocalizationsInput","kind":"INPUT_OBJECT"},{"name":"ShoesVariantCreateManyInlineInput","kind":"INPUT_OBJECT"},{"name":"ShoesVariantCreateOneInlineInput","kind":"INPUT_OBJECT"},{"name":"ShoesVariantCreateWithPositionInput","kind":"INPUT_OBJECT"},{"name":"ShoesVariantEdge","kind":"OBJECT"},{"name":"ShoesVariantManyWhereInput","kind":"INPUT_OBJECT"},{"name":"ShoesVariantOrderByInput","kind":"ENUM"},{"name":"ShoesVariantParent","kind":"UNION"},{"name":"ShoesVariantParentConnectInput","kind":"INPUT_OBJECT"},{"name":"ShoesVariantParentCreateInput","kind":"INPUT_OBJECT"},{"name":"ShoesVariantParentCreateManyInlineInput","kind":"INPUT_OBJECT"},{"name":"ShoesVariantParentCreateOneInlineInput","kind":"INPUT_OBJECT"},{"name":"ShoesVariantParentUpdateInput","kind":"INPUT_OBJECT"},{"name":"ShoesVariantParentUpdateManyInlineInput","kind":"INPUT_OBJECT"},{"name":"ShoesVariantParentUpdateManyWithNestedWhereInput","kind":"INPUT_OBJECT"},{"name":"ShoesVariantParentUpdateOneInlineInput","kind":"INPUT_OBJECT"},{"name":"ShoesVariantParentUpdateWithNestedWhereUniqueInput","kind":"INPUT_OBJECT"},{"name":"ShoesVariantParentUpsertWithNestedWhereUniqueInput","kind":"INPUT_OBJECT"},{"name":"ShoesVariantParentWhereInput","kind":"INPUT_OBJECT"},{"name":"ShoesVariantParentWhereUniqueInput","kind":"INPUT_OBJECT"},{"name":"ShoesVariantUpdateInput","kind":"INPUT_OBJECT"},{"name":"ShoesVariantUpdateLocalizationDataInput","kind":"INPUT_OBJECT"},{"name":"ShoesVariantUpdateLocalizationInput","kind":"INPUT_OBJECT"},{"name":"ShoesVariantUpdateLocalizationsInput","kind":"INPUT_OBJECT"},{"name":"ShoesVariantUpdateManyInlineInput","kind":"INPUT_OBJECT"},{"name":"ShoesVariantUpdateManyInput","kind":"INPUT_OBJECT"},{"name":"ShoesVariantUpdateManyLocalizationDataInput","kind":"INPUT_OBJECT"},{"name":"ShoesVariantUpdateManyLocalizationInput","kind":"INPUT_OBJECT"},{"name":"ShoesVariantUpdateManyLocalizationsInput","kind":"INPUT_OBJECT"},{"name":"ShoesVariantUpdateManyWithNestedWhereInput","kind":"INPUT_OBJECT"},{"name":"ShoesVariantUpdateOneInlineInput","kind":"INPUT_OBJECT"},{"name":"ShoesVariantUpdateWithNestedWhereUniqueAndPositionInput","kind":"INPUT_OBJECT"},{"name":"ShoesVariantUpdateWithNestedWhereUniqueInput","kind":"INPUT_OBJECT"},{"name":"ShoesVariantUpsertInput","kind":"INPUT_OBJECT"},{"name":"ShoesVariantUpsertLocalizationInput","kind":"INPUT_OBJECT"},{"name":"ShoesVariantUpsertWithNestedWhereUniqueAndPositionInput","kind":"INPUT_OBJECT"},{"name":"ShoesVariantUpsertWithNestedWhereUniqueInput","kind":"INPUT_OBJECT"},{"name":"ShoesVariantWhereInput","kind":"INPUT_OBJECT"},{"name":"ShoesVariantWhereUniqueInput","kind":"INPUT_OBJECT"},{"name":"Stage","kind":"ENUM"},{"name":"String","kind":"SCALAR"},{"name":"SystemDateTimeFieldVariation","kind":"ENUM"},{"name":"TaxonomyNode","kind":"OBJECT"},{"name":"TaxonomyNodeInput","kind":"INPUT_OBJECT"},{"name":"TaxonomyNodeWhereInput","kind":"INPUT_OBJECT"},{"name":"TaxonomyPathNode","kind":"OBJECT"},{"name":"UnpublishLocaleInput","kind":"INPUT_OBJECT"},{"name":"User","kind":"OBJECT"},{"name":"UserConnectInput","kind":"INPUT_OBJECT"},{"name":"UserConnection","kind":"OBJECT"},{"name":"UserCreateManyInlineInput","kind":"INPUT_OBJECT"},{"name":"UserCreateOneInlineInput","kind":"INPUT_OBJECT"},{"name":"UserEdge","kind":"OBJECT"},{"name":"UserKind","kind":"ENUM"},{"name":"UserManyWhereInput","kind":"INPUT_OBJECT"},{"name":"UserOrderByInput","kind":"ENUM"},{"name":"UserUpdateManyInlineInput","kind":"INPUT_OBJECT"},{"name":"UserUpdateOneInlineInput","kind":"INPUT_OBJECT"},{"name":"UserWhereComparatorInput","kind":"INPUT_OBJECT"},{"name":"UserWhereInput","kind":"INPUT_OBJECT"},{"name":"UserWhereStageInput","kind":"INPUT_OBJECT"},{"name":"UserWhereUniqueInput","kind":"INPUT_OBJECT"},{"name":"Version","kind":"OBJECT"},{"name":"VersionWhereInput","kind":"INPUT_OBJECT"},{"name":"Workflow","kind":"ENUM"},{"name":"_FilterKind","kind":"ENUM"},{"name":"_MutationInputFieldKind","kind":"ENUM"},{"name":"_MutationKind","kind":"ENUM"},{"name":"_OrderDirection","kind":"ENUM"},{"name":"_RelationInputCardinality","kind":"ENUM"},{"name":"_RelationInputKind","kind":"ENUM"},{"name":"_RelationKind","kind":"ENUM"},{"name":"_SystemDateTimeFieldVariation","kind":"ENUM"},{"name":"buttonCtaButtonTarget_c9duj","kind":"UNION"},{"name":"buttonCtaButtonTarget_c9dujConnectInput","kind":"INPUT_OBJECT"},{"name":"buttonCtaButtonTarget_c9dujCreateInput","kind":"INPUT_OBJECT"},{"name":"buttonCtaButtonTarget_c9dujCreateManyInlineInput","kind":"INPUT_OBJECT"},{"name":"buttonCtaButtonTarget_c9dujCreateOneInlineInput","kind":"INPUT_OBJECT"},{"name":"buttonCtaButtonTarget_c9dujUpdateInput","kind":"INPUT_OBJECT"},{"name":"buttonCtaButtonTarget_c9dujUpdateManyInlineInput","kind":"INPUT_OBJECT"},{"name":"buttonCtaButtonTarget_c9dujUpdateManyWithNestedWhereInput","kind":"INPUT_OBJECT"},{"name":"buttonCtaButtonTarget_c9dujUpdateOneInlineInput","kind":"INPUT_OBJECT"},{"name":"buttonCtaButtonTarget_c9dujUpdateWithNestedWhereUniqueInput","kind":"INPUT_OBJECT"},{"name":"buttonCtaButtonTarget_c9dujUpsertWithNestedWhereUniqueInput","kind":"INPUT_OBJECT"},{"name":"buttonCtaButtonTarget_c9dujWhereInput","kind":"INPUT_OBJECT"},{"name":"buttonCtaButtonTarget_c9dujWhereUniqueInput","kind":"INPUT_OBJECT"},{"name":"navItemTarget","kind":"UNION"},{"name":"navItemTargetConnectInput","kind":"INPUT_OBJECT"},{"name":"navItemTargetCreateInput","kind":"INPUT_OBJECT"},{"name":"navItemTargetCreateManyInlineInput","kind":"INPUT_OBJECT"},{"name":"navItemTargetCreateOneInlineInput","kind":"INPUT_OBJECT"},{"name":"navItemTargetUpdateInput","kind":"INPUT_OBJECT"},{"name":"navItemTargetUpdateManyInlineInput","kind":"INPUT_OBJECT"},{"name":"navItemTargetUpdateManyWithNestedWhereInput","kind":"INPUT_OBJECT"},{"name":"navItemTargetUpdateOneInlineInput","kind":"INPUT_OBJECT"},{"name":"navItemTargetUpdateWithNestedWhereUniqueInput","kind":"INPUT_OBJECT"},{"name":"navItemTargetUpsertWithNestedWhereUniqueInput","kind":"INPUT_OBJECT"},{"name":"navItemTargetWhereInput","kind":"INPUT_OBJECT"},{"name":"navItemTargetWhereUniqueInput","kind":"INPUT_OBJECT"}]}}}